[
    {
        "channel_name": "المحور",
        "channel_logo": "https://media0101.elcinema.com/tvguide/1145_2.png",
        "programs": [
            {
                "name": "فيلم",
                "time": "12:00 صباحاً - 03:00 صباحاً",
                "type": "",
                "link": ""
            },
            {
                "name": "زلزال",
                "time": "03:00 صباحاً - 04:00 صباحاً",
                "type": "مسلسل (2019)",
                "link": "https://elcinema.com/work/2006065/"
            }
        ]
    },
    {
        "channel_name": "الشرقية",
        "channel_logo": "https://media0101.elcinema.com/tvguide/1269_2.png",
        "programs": [
            {
                "name": "زلزال",
                "time": "01:00 صباحاً - 01:45 صباحاً",
                "type": "مسلسل (2019)",
                "link": "https://elcinema.com/work/2006065/"
            },
            {
                "name": "برنامج كلام الناس",
                "time": "01:45 صباحاً - 03:00 صباحاً",
                "type": "",
                "link": ""
            },
            {
                "name": "برنامج",
                "time": "03:00 صباحاً - 04:00 صباحاً",
                "type": "",
                "link": ""
            }
        ]
    },
    {
        "channel_name": "إم بي سي 2",
        "channel_logo": "https://media0101.elcinema.com/tvguide/1128_2.png",
        "programs": [
            {
                "name": "Spider-Man: No Way Home",
                "time": "12:30 صباحاً - 03:00 صباحاً",
                "type": "فيلم (2021)",
                "link": "https://elcinema.com/work/2065787/"
            },
            {
                "name": "Beast",
                "time": "03:00 صباحاً - 04:40 صباحاً",
                "type": "فيلم (2022)",
                "link": "https://elcinema.com/work/2074573/"
            }
        ]
    },
    {
        "channel_name": "صدى البلد",
        "channel_logo": "https://media0101.elcinema.com/tvguide/1226_2.png",
        "programs": [
            {
                "name": "ريا وسكينة",
                "time": "01:00 صباحاً - 02:00 صباحاً",
                "type": "مسلسل (2005)",
                "link": "https://elcinema.com/work/1326791/"
            },
            {
                "name": "برنامج",
                "time": "02:00 صباحاً - 03:00 صباحاً",
                "type": "",
                "link": ""
            },
            {
                "name": "برنامج",
                "time": "03:00 صباحاً - 04:00 صباحاً",
                "type": "",
                "link": ""
            }
        ]
    },
    {
        "channel_name": "أبو ظبي",
        "channel_logo": "https://media0101.elcinema.com/tvguide/1136_2.png",
        "programs": [
            {
                "name": "برنامج Made in u.a.e",
                "time": "01:00 صباحاً - 02:00 صباحاً",
                "type": "",
                "link": ""
            },
            {
                "name": "أبو العروسة",
                "time": "02:00 صباحاً - 03:00 صباحاً",
                "type": "مسلسل (2017)",
                "link": "https://elcinema.com/work/2049280/"
            },
            {
                "name": "بيت أهلي",
                "time": "03:00 صباحاً - 03:30 صباحاً",
                "type": "مسلسل (2024)",
                "link": "https://elcinema.com/work/2083725/"
            }
        ]
    },
    {
        "channel_name": "عمان",
        "channel_logo": "https://media0101.elcinema.com/tvguide/1317_2.png",
        "programs": [
            {
                "name": "فهد البطل",
                "time": "12:50 صباحاً - 01:15 صباحاً",
                "type": "مسلسل (2025)",
                "link": "https://elcinema.com/work/2088310/"
            },
            {
                "name": "برنامج قهوة الصباح",
                "time": "01:15 صباحاً - 02:10 صباحاً",
                "type": "",
                "link": ""
            },
            {
                "name": "خط أحمر",
                "time": "02:10 صباحاً - 02:40 صباحاً",
                "type": "مسلسل (2022)",
                "link": "https://elcinema.com/work/2075173/"
            },
            {
                "name": "برنامج - أحسن القصص",
                "time": "02:40 صباحاً - 03:00 صباحاً",
                "type": "",
                "link": ""
            },
            {
                "name": "برنامج من عمان",
                "time": "03:00 صباحاً - 03:45 صباحاً",
                "type": "",
                "link": ""
            }
        ]
    },
    {
        "channel_name": "ديسكفري",
        "channel_logo": "https://media0101.elcinema.com/tvguide/1272_2.png",
        "programs": [
            {
                "name": "Gold Divers  -  Big Cold Gold",
                "time": "12:27 صباحاً - 01:18 صباحاً",
                "type": "",
                "link": ""
            },
            {
                "name": "How Do They Do It?  -  Wine And More",
                "time": "01:18 صباحاً - 01:48 صباحاً",
                "type": "",
                "link": ""
            },
            {
                "name": "Wheeler dealers  -  The British Are Leaving",
                "time": "01:48 صباحاً - 02:38 صباحاً",
                "type": "",
                "link": ""
            },
            {
                "name": "Wheeler dealers  -  Mini Mark 1 850",
                "time": "02:38 صباحاً - 03:28 صباحاً",
                "type": "",
                "link": ""
            },
            {
                "name": "Expedition Unknown  -  Egypt's City Of The Dead",
                "time": "03:28 صباحاً - 04:14 صباحاً",
                "type": "",
                "link": ""
            }
        ]
    },
    {
        "channel_name": "ذكريات",
        "channel_logo": "https://media0101.elcinema.com/tvguide/1366_2.png",
        "programs": [
            {
                "name": "عائلة فوق تنور ساخن",
                "time": "01:00 صباحاً - 02:00 صباحاً",
                "type": "مسلسل (1987)",
                "link": "https://elcinema.com/work/1384403/"
            },
            {
                "name": "شجرة الدر",
                "time": "02:00 صباحاً - 03:00 صباحاً",
                "type": "مسلسل (1979)",
                "link": "https://elcinema.com/work/2008176/"
            },
            {
                "name": "برنامج شريط الفنون",
                "time": "03:00 صباحاً - 04:00 صباحاً",
                "type": "",
                "link": ""
            }
        ]
    },
    {
        "channel_name": "ميكس وان",
        "channel_logo": "https://media0101.elcinema.com/tvguide/1373_2.png",
        "programs": [
            {
                "name": "فيلم",
                "time": "11:00 مساءً - 02:00 صباحاً",
                "type": "",
                "link": ""
            },
            {
                "name": "Forbidden Love",
                "time": "02:00 صباحاً - 03:00 صباحاً",
                "type": "مسلسل (2008)",
                "link": "https://elcinema.com/work/1997628/"
            },
            {
                "name": "ومن الحب ما قتل  2",
                "time": "03:00 صباحاً - 04:00 صباحاً",
                "type": "مسلسل (2016)",
                "link": "https://elcinema.com/work/2059705/"
            }
        ]
    },
    {
        "channel_name": "النهار",
        "channel_logo": "https://media0101.elcinema.com/tvguide/1193_2.png",
        "programs": [
            {
                "name": "آخر النهار",
                "time": "01:00 صباحاً - 02:00 صباحاً",
                "type": "ﺑﺮﻧﺎﻣﺞ (2011)",
                "link": "https://elcinema.com/work/2009974/"
            },
            {
                "name": "إسأل مع دعاء",
                "time": "02:00 صباحاً - 02:30 صباحاً",
                "type": "ﺑﺮﻧﺎﻣﺞ (2018)",
                "link": "https://elcinema.com/work/2051634/"
            },
            {
                "name": "برنامج أوضة اللبس",
                "time": "02:30 صباحاً - 03:00 صباحاً",
                "type": "",
                "link": ""
            },
            {
                "name": "برنامج",
                "time": "03:00 صباحاً - 04:00 صباحاً",
                "type": "",
                "link": ""
            }
        ]
    },
    {
        "channel_name": "السومرية",
        "channel_logo": "https://media0101.elcinema.com/tvguide/1301_2.png",
        "programs": [
            {
                "name": "برنامج live talk",
                "time": "12:00 صباحاً - 01:30 صباحاً",
                "type": "",
                "link": ""
            },
            {
                "name": "برنامج ناس وناس",
                "time": "01:30 صباحاً - 02:00 صباحاً",
                "type": "",
                "link": ""
            },
            {
                "name": "برنامج مايك السومرية",
                "time": "02:00 صباحاً - 03:00 صباحاً",
                "type": "",
                "link": ""
            },
            {
                "name": "ورود ملونة",
                "time": "03:00 صباحاً - 04:30 صباحاً",
                "type": "مسلسل (2020)",
                "link": "https://elcinema.com/work/2007920/"
            }
        ]
    },
    {
        "channel_name": "دبي",
        "channel_logo": "https://media0101.elcinema.com/tvguide/1169_2.png",
        "programs": [
            {
                "name": "Mehmed: Fetihler Sultani S2",
                "time": "12:30 صباحاً - 01:30 صباحاً",
                "type": "مسلسل (2024)",
                "link": "https://elcinema.com/work/2098117/"
            },
            {
                "name": "برنامج منصات رقمية",
                "time": "01:30 صباحاً - 02:00 صباحاً",
                "type": "",
                "link": ""
            },
            {
                "name": "دبي هذا الصباح",
                "time": "02:00 صباحاً - 03:00 صباحاً",
                "type": "ﺑﺮﻧﺎﻣﺞ (2015)",
                "link": "https://elcinema.com/work/2040996/"
            },
            {
                "name": "برنامج منصات رقمية",
                "time": "03:00 صباحاً - 03:30 صباحاً",
                "type": "",
                "link": ""
            }
        ]
    },
    {
        "channel_name": "القاهرة والناس 2",
        "channel_logo": "https://media0101.elcinema.com/tvguide/1252_2.png",
        "programs": [
            {
                "name": "برنامج حديث القاهرة",
                "time": "01:00 صباحاً - 02:52 صباحاً",
                "type": "",
                "link": ""
            },
            {
                "name": "برنامج تحدي الأزواج",
                "time": "02:52 صباحاً - 04:00 صباحاً",
                "type": "",
                "link": ""
            }
        ]
    },
    {
        "channel_name": "المغربية الثانية",
        "channel_logo": "https://media0101.elcinema.com/tvguide/1353_2.png",
        "programs": [
            {
                "name": "البحر الأسود",
                "time": "12:45 صباحاً - 02:00 صباحاً",
                "type": "مسلسل (2018)",
                "link": "https://elcinema.com/work/2061768/"
            },
            {
                "name": "برنامج",
                "time": "02:00 صباحاً - 03:35 صباحاً",
                "type": "",
                "link": ""
            }
        ]
    },
    {
        "channel_name": "بي إن موفيز بريمير",
        "channel_logo": "https://media0101.elcinema.com/tvguide/1322_2.png",
        "programs": [
            {
                "name": "The Moogai",
                "time": "11:45 مساءً - 01:15 صباحاً",
                "type": "فيلم (2024)",
                "link": "https://elcinema.com/work/2097742/"
            },
            {
                "name": "Whispers in the Walls",
                "time": "01:15 صباحاً - 03:00 صباحاً",
                "type": "فيلم (2024)",
                "link": "https://elcinema.com/work/2092961/"
            },
            {
                "name": "Other People's Children",
                "time": "03:00 صباحاً - 04:30 صباحاً",
                "type": "فيلم (2022)",
                "link": "https://elcinema.com/work/2084514/"
            }
        ]
    },
    {
        "channel_name": "بي إن سيريس إتش دي 2",
        "channel_logo": "https://media0101.elcinema.com/tvguide/1328_2.png",
        "programs": [
            {
                "name": "The Alienist S2",
                "time": "01:00 صباحاً - 02:00 صباحاً",
                "type": "مسلسل (2020)",
                "link": "https://elcinema.com/work/2097470/"
            },
            {
                "name": "The Real CSI: Miami",
                "time": "02:00 صباحاً - 03:00 صباحاً",
                "type": "مسلسل (2024)",
                "link": "https://elcinema.com/work/2095445/"
            },
            {
                "name": "Dexter: New Blood",
                "time": "03:00 صباحاً - 04:00 صباحاً",
                "type": "مسلسل (2021)",
                "link": "https://elcinema.com/work/2066517/"
            }
        ]
    },
    {
        "channel_name": "روتانا سينما",
        "channel_logo": "https://media0101.elcinema.com/tvguide/1289_2.png",
        "programs": [
            {
                "name": "المدمن",
                "time": "01:00 صباحاً - 03:00 صباحاً",
                "type": "فيلم (1983)",
                "link": "https://elcinema.com/work/1004630/"
            },
            {
                "name": "عندليب الدقي",
                "time": "03:00 صباحاً - 05:00 صباحاً",
                "type": "فيلم (2007)",
                "link": "https://elcinema.com/work/1001611/"
            }
        ]
    },
    {
        "channel_name": "إم بي سي 4",
        "channel_logo": "https://media0101.elcinema.com/tvguide/1129_2.png",
        "programs": [
            {
                "name": "الثمن",
                "time": "01:00 صباحاً - 01:45 صباحاً",
                "type": "مسلسل (2023)",
                "link": "https://elcinema.com/work/2076120/"
            },
            {
                "name": "Kiskanmak",
                "time": "01:45 صباحاً - 02:15 صباحاً",
                "type": "مسلسل (2025)",
                "link": "https://elcinema.com/work/2096859/"
            },
            {
                "name": "Kral Kaybederse",
                "time": "02:15 صباحاً - 02:45 صباحاً",
                "type": "مسلسل (2025)",
                "link": "https://elcinema.com/work/2093145/"
            },
            {
                "name": "Uzak Sehir",
                "time": "02:45 صباحاً - 03:20 صباحاً",
                "type": "مسلسل (2024)",
                "link": "https://elcinema.com/work/2091404/"
            },
            {
                "name": "في الظل",
                "time": "03:20 صباحاً - 03:50 صباحاً",
                "type": "مسلسل (2026)",
                "link": "https://elcinema.com/work/2099606/"
            }
        ]
    },
    {
        "channel_name": "يو تي في",
        "channel_logo": "https://media0101.elcinema.com/tvguide/1367_2.png",
        "programs": [
            {
                "name": "برنامج",
                "time": "01:00 صباحاً - 02:00 صباحاً",
                "type": "",
                "link": ""
            },
            {
                "name": "عودة المنتقم",
                "time": "02:00 صباحاً - 03:00 صباحاً",
                "type": "مسلسل (2017)",
                "link": "https://elcinema.com/work/2056948/"
            },
            {
                "name": "برنامج هاتريك",
                "time": "03:00 صباحاً - 04:00 صباحاً",
                "type": "",
                "link": ""
            }
        ]
    },
    {
        "channel_name": "ال تي في",
        "channel_logo": "https://media0101.elcinema.com/tvguide/1313_2.png",
        "programs": [
            {
                "name": "سيرة الحب",
                "time": "01:00 صباحاً - 02:00 صباحاً",
                "type": "مسلسل (2007)",
                "link": "https://elcinema.com/work/1285399/"
            },
            {
                "name": "أخبار",
                "time": "02:00 صباحاً - 03:00 صباحاً",
                "type": "",
                "link": ""
            },
            {
                "name": "جري الوحوش",
                "time": "03:00 صباحاً - 04:00 صباحاً",
                "type": "مسلسل (2024)",
                "link": "https://elcinema.com/work/2083113/"
            }
        ]
    },
    {
        "channel_name": "المصرية",
        "channel_logo": "https://media0101.elcinema.com/tvguide/1119_2.png",
        "programs": [
            {
                "name": "برنامج",
                "time": "01:00 صباحاً - 02:00 صباحاً",
                "type": "",
                "link": ""
            },
            {
                "name": "برنامج",
                "time": "02:00 صباحاً - 03:00 صباحاً",
                "type": "",
                "link": ""
            },
            {
                "name": "برنامج",
                "time": "03:00 صباحاً - 04:00 صباحاً",
                "type": "",
                "link": ""
            }
        ]
    },
    {
        "channel_name": "روتانا أفلام بلاس",
        "channel_logo": "https://media0101.elcinema.com/tvguide/1218_2.png",
        "programs": [
            {
                "name": "بلاغ للرأي العام",
                "time": "01:00 صباحاً - 02:30 صباحاً",
                "type": "فيلم (1990)",
                "link": "https://elcinema.com/work/1026306/"
            },
            {
                "name": "دم الغزال",
                "time": "02:30 صباحاً - 04:00 صباحاً",
                "type": "فيلم (2005)",
                "link": "https://elcinema.com/work/2056027/"
            }
        ]
    },
    {
        "channel_name": "إم بي سي دراما",
        "channel_logo": "https://media0101.elcinema.com/tvguide/1194_2.png",
        "programs": [
            {
                "name": "إش إش",
                "time": "01:00 صباحاً - 02:00 صباحاً",
                "type": "مسلسل (2025)",
                "link": "https://elcinema.com/work/2087894/"
            },
            {
                "name": "للمعاريس فقط",
                "time": "02:00 صباحاً - 03:00 صباحاً",
                "type": "مسلسل (2025)",
                "link": "https://elcinema.com/work/2089963/"
            },
            {
                "name": "ستيلتو",
                "time": "03:00 صباحاً - 04:00 صباحاً",
                "type": "مسلسل (2022)",
                "link": "https://elcinema.com/work/2071513/"
            }
        ]
    },
    {
        "channel_name": "أو إس إن كيدز",
        "channel_logo": "https://media0101.elcinema.com/tvguide/1232_2.png",
        "programs": [
            {
                "name": "Matt Hatter Chronicles S2",
                "time": "12:48 صباحاً - 01:10 صباحاً",
                "type": "مسلسل - ﺭﺳﻮﻡ ﻣﺘﺤﺮﻛﺔ (2012)",
                "link": "https://elcinema.com/work/2095795/"
            },
            {
                "name": "Matt Hatter Chronicles S2",
                "time": "01:10 صباحاً - 01:32 صباحاً",
                "type": "مسلسل - ﺭﺳﻮﻡ ﻣﺘﺤﺮﻛﺔ (2012)",
                "link": "https://elcinema.com/work/2095795/"
            },
            {
                "name": "Bing",
                "time": "01:32 صباحاً - 01:42 صباحاً",
                "type": "مسلسل - ﺭﺳﻮﻡ ﻣﺘﺤﺮﻛﺔ (2014)",
                "link": "https://elcinema.com/work/2096162/"
            },
            {
                "name": "Bing",
                "time": "01:42 صباحاً - 01:52 صباحاً",
                "type": "مسلسل - ﺭﺳﻮﻡ ﻣﺘﺤﺮﻛﺔ (2014)",
                "link": "https://elcinema.com/work/2096162/"
            },
            {
                "name": "منصور 2",
                "time": "01:52 صباحاً - 02:03 صباحاً",
                "type": "مسلسل (2016)",
                "link": "https://elcinema.com/work/2025268/"
            },
            {
                "name": "منصور 2",
                "time": "02:03 صباحاً - 02:14 صباحاً",
                "type": "مسلسل (2016)",
                "link": "https://elcinema.com/work/2025268/"
            },
            {
                "name": "منصور 2",
                "time": "02:14 صباحاً - 02:25 صباحاً",
                "type": "مسلسل (2016)",
                "link": "https://elcinema.com/work/2025268/"
            },
            {
                "name": "منصور 2",
                "time": "02:25 صباحاً - 02:36 صباحاً",
                "type": "مسلسل (2016)",
                "link": "https://elcinema.com/work/2025268/"
            },
            {
                "name": "منصور 2",
                "time": "02:36 صباحاً - 02:47 صباحاً",
                "type": "مسلسل (2016)",
                "link": "https://elcinema.com/work/2025268/"
            },
            {
                "name": "منصور 2",
                "time": "02:47 صباحاً - 03:00 صباحاً",
                "type": "مسلسل (2016)",
                "link": "https://elcinema.com/work/2025268/"
            },
            {
                "name": "Charlie and Lola S2",
                "time": "03:00 صباحاً - 03:13 صباحاً",
                "type": "مسلسل (2006)",
                "link": "https://elcinema.com/work/2099553/"
            },
            {
                "name": "Charlie and Lola S2",
                "time": "03:13 صباحاً - 03:26 صباحاً",
                "type": "مسلسل (2006)",
                "link": "https://elcinema.com/work/2099553/"
            },
            {
                "name": "Charlie and Lola S2",
                "time": "03:26 صباحاً - 03:39 صباحاً",
                "type": "مسلسل (2006)",
                "link": "https://elcinema.com/work/2099553/"
            }
        ]
    },
    {
        "channel_name": "إم بي سي مصر",
        "channel_logo": "https://media0101.elcinema.com/tvguide/1239_2.png",
        "programs": [
            {
                "name": "اللعيب",
                "time": "11:50 مساءً - 01:15 صباحاً",
                "type": "ﺑﺮﻧﺎﻣﺞ (2018)",
                "link": "https://elcinema.com/work/2085784/"
            },
            {
                "name": "ليه لأ؟! 3",
                "time": "01:15 صباحاً - 02:10 صباحاً",
                "type": "مسلسل (2023)",
                "link": "https://elcinema.com/work/2076745/"
            },
            {
                "name": "Golden Boy S2",
                "time": "02:10 صباحاً - 03:00 صباحاً",
                "type": "مسلسل (2023)",
                "link": "https://elcinema.com/work/2083608/"
            },
            {
                "name": "العتاولة 2",
                "time": "03:00 صباحاً - 04:01 صباحاً",
                "type": "مسلسل (2025)",
                "link": "https://elcinema.com/work/2089649/"
            }
        ]
    },
    {
        "channel_name": "الأولى المغربية",
        "channel_logo": "https://media0101.elcinema.com/tvguide/1312_2.png",
        "programs": [
            {
                "name": "عام ونهار",
                "time": "01:00 صباحاً - 01:35 صباحاً",
                "type": "مسلسل (2024)",
                "link": "https://elcinema.com/work/2086528/"
            },
            {
                "name": "إلا ضاق الحال",
                "time": "01:35 صباحاً - 02:30 صباحاً",
                "type": "مسلسل (2023)",
                "link": "https://elcinema.com/work/2078028/"
            },
            {
                "name": "برنامج وراء الستار",
                "time": "02:30 صباحاً - 03:00 صباحاً",
                "type": "",
                "link": ""
            },
            {
                "name": "قناة اطلس",
                "time": "03:00 صباحاً - 04:00 صباحاً",
                "type": "",
                "link": ""
            }
        ]
    },
    {
        "channel_name": "دبي وان",
        "channel_logo": "https://media0101.elcinema.com/tvguide/1173_2.png",
        "programs": [
            {
                "name": "2 Good 2 Be True",
                "time": "01:00 صباحاً - 02:00 صباحاً",
                "type": "مسلسل (2022)",
                "link": "https://elcinema.com/work/2095453/"
            },
            {
                "name": "Midnight Sun",
                "time": "02:00 صباحاً - 04:00 صباحاً",
                "type": "فيلم (2018)",
                "link": "https://elcinema.com/work/2044186/"
            }
        ]
    },
    {
        "channel_name": "زي ألوان",
        "channel_logo": "https://media0101.elcinema.com/tvguide/1261_2.png",
        "programs": [
            {
                "name": "انا معك",
                "time": "01:00 صباحاً - 02:00 صباحاً",
                "type": "مسلسل (2024)",
                "link": "https://elcinema.com/work/2098288/"
            },
            {
                "name": "Kundali Bhagya",
                "time": "02:00 صباحاً - 03:00 صباحاً",
                "type": "مسلسل (2017)",
                "link": "https://elcinema.com/work/2061760/"
            },
            {
                "name": "ليالي روكسي",
                "time": "03:00 صباحاً - 04:00 صباحاً",
                "type": "مسلسل (2025)",
                "link": "https://elcinema.com/work/2088942/"
            }
        ]
    },
    {
        "channel_name": "الأردن",
        "channel_logo": "https://media0101.elcinema.com/tvguide/1314_2.png",
        "programs": [
            {
                "name": "برنامج مسارات",
                "time": "01:00 صباحاً - 02:00 صباحاً",
                "type": "",
                "link": ""
            },
            {
                "name": "وعد الغريب",
                "time": "02:00 صباحاً - 03:00 صباحاً",
                "type": "مسلسل (2016)",
                "link": "https://elcinema.com/work/2035832/"
            },
            {
                "name": "برنامج",
                "time": "03:00 صباحاً - 04:00 صباحاً",
                "type": "",
                "link": ""
            }
        ]
    },
    {
        "channel_name": "روتانا خليجية",
        "channel_logo": "https://media0101.elcinema.com/tvguide/1149_2.png",
        "programs": [
            {
                "name": "برنامج يا هلا",
                "time": "12:00 صباحاً - 01:30 صباحاً",
                "type": "",
                "link": ""
            },
            {
                "name": "برنامج وينك",
                "time": "01:30 صباحاً - 02:30 صباحاً",
                "type": "",
                "link": ""
            },
            {
                "name": "ضمير مستتر",
                "time": "02:30 صباحاً - 03:30 صباحاً",
                "type": "مسلسل - ﻗﺼﻴﺮ (2026)",
                "link": "https://elcinema.com/work/2075312/"
            }
        ]
    },
    {
        "channel_name": "روتانا سينما مصر",
        "channel_logo": "https://media0101.elcinema.com/tvguide/1148_2.png",
        "programs": [
            {
                "name": "زوجة رجل مهم",
                "time": "01:00 صباحاً - 03:00 صباحاً",
                "type": "فيلم (1988)",
                "link": "https://elcinema.com/work/1010226/"
            },
            {
                "name": "الغواص",
                "time": "03:00 صباحاً - 05:00 صباحاً",
                "type": "فيلم (2006)",
                "link": "https://elcinema.com/work/1007409/"
            }
        ]
    },
    {
        "channel_name": "إم بي سي مصر 2",
        "channel_logo": "https://media0101.elcinema.com/tvguide/1278_2.png",
        "programs": [
            {
                "name": "Aashiqana",
                "time": "12:30 صباحاً - 01:15 صباحاً",
                "type": "مسلسل (2022)",
                "link": "https://elcinema.com/work/2093146/"
            },
            {
                "name": "عائلة الحاج نعمان ج1",
                "time": "01:15 صباحاً - 02:00 صباحاً",
                "type": "مسلسل (2017)",
                "link": "https://elcinema.com/work/2047460/"
            },
            {
                "name": "عشم إبليس",
                "time": "02:00 صباحاً - 02:45 صباحاً",
                "type": "مسلسل (2017)",
                "link": "https://elcinema.com/work/1768421/"
            },
            {
                "name": "صباحك مصري",
                "time": "02:45 صباحاً - 04:00 صباحاً",
                "type": "ﺑﺮﻧﺎﻣﺞ (2014)",
                "link": "https://elcinema.com/work/2034283/"
            }
        ]
    },
    {
        "channel_name": "ماسة",
        "channel_logo": "https://media0101.elcinema.com/tvguide/1401_2.png",
        "programs": [
            {
                "name": "ورطة بابا",
                "time": "12:35 صباحاً - 01:05 صباحاً",
                "type": "مسلسل (2023)",
                "link": "https://elcinema.com/work/2099622/"
            },
            {
                "name": "برنامج في المخفر",
                "time": "01:05 صباحاً - 02:30 صباحاً",
                "type": "",
                "link": ""
            },
            {
                "name": "سوق الديرة",
                "time": "02:30 صباحاً - 03:10 صباحاً",
                "type": "مسلسل (2026)",
                "link": "https://elcinema.com/work/2098940/"
            },
            {
                "name": "برنامج تذكرة سفر",
                "time": "03:10 صباحاً - 04:00 صباحاً",
                "type": "",
                "link": ""
            }
        ]
    },
    {
        "channel_name": "أو إس إن موفيز هوليوود",
        "channel_logo": "https://media0101.elcinema.com/tvguide/1391_2.png",
        "programs": [
            {
                "name": "The Notebook",
                "time": "12:35 صباحاً - 02:50 صباحاً",
                "type": "فيلم (2004)",
                "link": "https://elcinema.com/work/2003106/"
            },
            {
                "name": "Million Dollar Baby",
                "time": "02:50 صباحاً - 05:20 صباحاً",
                "type": "فيلم (2004)",
                "link": "https://elcinema.com/work/2001959/"
            }
        ]
    },
    {
        "channel_name": "الوسط",
        "channel_logo": "https://media0101.elcinema.com/tvguide/1383_2.png",
        "programs": [
            {
                "name": "برنامج",
                "time": "01:00 صباحاً - 02:00 صباحاً",
                "type": "",
                "link": ""
            },
            {
                "name": "برنامج ملعب الوسط",
                "time": "02:00 صباحاً - 04:00 صباحاً",
                "type": "",
                "link": ""
            }
        ]
    },
    {
        "channel_name": "سي بي سي دراما",
        "channel_logo": "https://media0101.elcinema.com/tvguide/1199_2.png",
        "programs": [
            {
                "name": "العيلة دي",
                "time": "01:00 صباحاً - 02:00 صباحاً",
                "type": "مسلسل (2022)",
                "link": "https://elcinema.com/work/2076576/"
            },
            {
                "name": "سوشيال",
                "time": "02:00 صباحاً - 03:00 صباحاً",
                "type": "مسلسل (2022)",
                "link": "https://elcinema.com/work/2072752/"
            },
            {
                "name": "راس الغول",
                "time": "03:00 صباحاً - 04:00 صباحاً",
                "type": "مسلسل (2016)",
                "link": "https://elcinema.com/work/2033147/"
            }
        ]
    },
    {
        "channel_name": "سما دبي",
        "channel_logo": "https://media0101.elcinema.com/tvguide/1177_2.png",
        "programs": [
            {
                "name": "برنامج الحي الثقافي",
                "time": "12:30 صباحاً - 01:30 صباحاً",
                "type": "",
                "link": ""
            },
            {
                "name": "البوشية",
                "time": "01:30 صباحاً - 02:30 صباحاً",
                "type": "مسلسل (2023)",
                "link": "https://elcinema.com/work/2076515/"
            },
            {
                "name": "برنامج يوم الخلود",
                "time": "02:30 صباحاً - 03:00 صباحاً",
                "type": "",
                "link": ""
            },
            {
                "name": "برنامج بصمات",
                "time": "03:00 صباحاً - 03:30 صباحاً",
                "type": "",
                "link": ""
            }
        ]
    },
    {
        "channel_name": "أو إس إن موفيز بريميير",
        "channel_logo": "https://media0101.elcinema.com/tvguide/1213_2.png",
        "programs": [
            {
                "name": "Aztec Batman: Clash of Empires",
                "time": "12:40 صباحاً - 02:10 صباحاً",
                "type": "فيلم - ﺭﺳﻮﻡ ﻣﺘﺤﺮﻛﺔ (2025)",
                "link": "https://elcinema.com/work/2099531/"
            },
            {
                "name": "Oracle",
                "time": "02:10 صباحاً - 03:50 صباحاً",
                "type": "فيلم (2023)",
                "link": "https://elcinema.com/work/2096740/"
            }
        ]
    },
    {
        "channel_name": "أون دراما",
        "channel_logo": "https://media0101.elcinema.com/tvguide/1134_2.png",
        "programs": [
            {
                "name": "سوق الكانتو",
                "time": "01:00 صباحاً - 02:00 صباحاً",
                "type": "مسلسل (2023)",
                "link": "https://elcinema.com/work/2077352/"
            },
            {
                "name": "ضد الكسر",
                "time": "02:00 صباحاً - 03:00 صباحاً",
                "type": "مسلسل (2021)",
                "link": "https://elcinema.com/work/2066783/"
            },
            {
                "name": "إلا أنا",
                "time": "03:00 صباحاً - 04:00 صباحاً",
                "type": "مسلسل (2020)",
                "link": "https://elcinema.com/work/2061816/"
            }
        ]
    },
    {
        "channel_name": "بي إن موفيز أكشن",
        "channel_logo": "https://media0101.elcinema.com/tvguide/1323_2.png",
        "programs": [
            {
                "name": "No Exit",
                "time": "12:45 صباحاً - 02:30 صباحاً",
                "type": "فيلم (2022)",
                "link": "https://elcinema.com/work/2073016/"
            },
            {
                "name": "Ghosts of Red Ridge",
                "time": "02:30 صباحاً - 04:00 صباحاً",
                "type": "فيلم (2024)",
                "link": "https://elcinema.com/work/2092196/"
            }
        ]
    },
    {
        "channel_name": "الحياة",
        "channel_logo": "https://media0101.elcinema.com/tvguide/1137_2.png",
        "programs": [
            {
                "name": "برنامج دولة التلاوة",
                "time": "01:00 صباحاً - 02:00 صباحاً",
                "type": "",
                "link": ""
            },
            {
                "name": "برنامج",
                "time": "02:00 صباحاً - 03:00 صباحاً",
                "type": "",
                "link": ""
            },
            {
                "name": "برنامج الدنيا بخير",
                "time": "03:00 صباحاً - 03:30 صباحاً",
                "type": "",
                "link": ""
            }
        ]
    },
    {
        "channel_name": "تلفزيون حضرموت",
        "channel_logo": "https://media0101.elcinema.com/tvguide/1374_2.png",
        "programs": [
            {
                "name": "برنامج",
                "time": "01:00 صباحاً - 02:00 صباحاً",
                "type": "",
                "link": ""
            },
            {
                "name": "برنامج",
                "time": "02:00 صباحاً - 03:00 صباحاً",
                "type": "",
                "link": ""
            },
            {
                "name": "فترة دينية",
                "time": "09:00  مساءً - 12:00  صباحًا",
                "type": "",
                "link": ""
            }
        ]
    },
    {
        "channel_name": "روتانا كوميدي",
        "channel_logo": "https://media0101.elcinema.com/tvguide/1358_2.png",
        "programs": [
            {
                "name": "أربعة في مهمة رسمية",
                "time": "01:00 صباحاً - 03:00 صباحاً",
                "type": "فيلم (1987)",
                "link": "https://elcinema.com/work/1284447/"
            },
            {
                "name": "أحلام الفتى الطايش",
                "time": "03:00 صباحاً - 05:00 صباحاً",
                "type": "فيلم (2007)",
                "link": "https://elcinema.com/work/1010963/"
            }
        ]
    },
    {
        "channel_name": "الظفرة",
        "channel_logo": "https://media0101.elcinema.com/tvguide/1264_2.png",
        "programs": [
            {
                "name": "زقاق الجن",
                "time": "01:00 صباحاً - 02:00 صباحاً",
                "type": "مسلسل (2023)",
                "link": "https://elcinema.com/work/2077858/"
            },
            {
                "name": "قلم رصاص",
                "time": "02:00 صباحاً - 03:00 صباحاً",
                "type": "مسلسل (2024)",
                "link": "https://elcinema.com/work/2081770/"
            },
            {
                "name": "نشميات من البادية",
                "time": "03:00 صباحاً - 04:00 صباحاً",
                "type": "مسلسل (2022)",
                "link": "https://elcinema.com/work/2073605/"
            }
        ]
    },
    {
        "channel_name": "بي إن دراما",
        "channel_logo": "https://media0101.elcinema.com/tvguide/1309_2.png",
        "programs": [
            {
                "name": "أفكار أمي",
                "time": "01:00 صباحاً - 02:00 صباحاً",
                "type": "مسلسل (2025)",
                "link": "https://elcinema.com/work/2088176/"
            },
            {
                "name": "نفس",
                "time": "02:00 صباحاً - 03:00 صباحاً",
                "type": "مسلسل (2025)",
                "link": "https://elcinema.com/work/2091703/"
            },
            {
                "name": "ملفات منسية",
                "time": "03:00 صباحاً - 04:00 صباحاً",
                "type": "مسلسل (2024)",
                "link": "https://elcinema.com/work/2083063/"
            }
        ]
    },
    {
        "channel_name": "الجديد",
        "channel_logo": "https://media0101.elcinema.com/tvguide/1216_2.png",
        "programs": [
            {
                "name": "برنامج",
                "time": "12:30 صباحاً - 01:30 صباحاً",
                "type": "",
                "link": ""
            },
            {
                "name": "برنامج",
                "time": "01:30 صباحاً - 02:30 صباحاً",
                "type": "",
                "link": ""
            },
            {
                "name": "برنامج",
                "time": "02:30 صباحاً - 03:30 صباحاً",
                "type": "",
                "link": ""
            }
        ]
    },
    {
        "channel_name": "صدى البلد 2",
        "channel_logo": "https://media0101.elcinema.com/tvguide/1279_2.png",
        "programs": [
            {
                "name": "برنامج",
                "time": "01:00 صباحاً - 02:00 صباحاً",
                "type": "",
                "link": ""
            },
            {
                "name": "برنامج",
                "time": "02:00 صباحاً - 03:00 صباحاً",
                "type": "",
                "link": ""
            },
            {
                "name": "برنامج",
                "time": "03:00 صباحاً - 04:00 صباحاً",
                "type": "",
                "link": ""
            }
        ]
    },
    {
        "channel_name": "بي إن موفيز دراما",
        "channel_logo": "https://media0101.elcinema.com/tvguide/1324_2.png",
        "programs": [
            {
                "name": "A Quiet Place",
                "time": "11:45 مساءً - 01:15 صباحاً",
                "type": "فيلم (2018)",
                "link": "https://elcinema.com/work/2049556/"
            },
            {
                "name": "Valentine's Town",
                "time": "01:15 صباحاً - 02:45 صباحاً",
                "type": "فيلم (2024)",
                "link": "https://elcinema.com/work/2092542/"
            },
            {
                "name": "Singing in My Sleep",
                "time": "02:45 صباحاً - 04:15 صباحاً",
                "type": "فيلم (2024)",
                "link": "https://elcinema.com/work/2092900/"
            }
        ]
    },
    {
        "channel_name": "بي إن موفيز فاميلي",
        "channel_logo": "https://media0101.elcinema.com/tvguide/1325_2.png",
        "programs": [
            {
                "name": "Panda Bear in Africa",
                "time": "12:45 صباحاً - 02:30 صباحاً",
                "type": "فيلم (2024)",
                "link": "https://elcinema.com/work/2088082/"
            },
            {
                "name": "Dogs at the Opera",
                "time": "02:30 صباحاً - 04:00 صباحاً",
                "type": "فيلم (2023)",
                "link": "https://elcinema.com/work/2084117/"
            }
        ]
    },
    {
        "channel_name": "ستار موفيز",
        "channel_logo": "https://media0101.elcinema.com/tvguide/1212_2.png",
        "programs": [
            {
                "name": "Bottom of the 9th",
                "time": "12:05 صباحاً - 01:55 صباحاً",
                "type": "فيلم (2019)",
                "link": "https://elcinema.com/work/2058143/"
            },
            {
                "name": "Long Shot",
                "time": "01:55 صباحاً - 03:50 صباحاً",
                "type": "فيلم (2019)",
                "link": "https://elcinema.com/work/2048900/"
            }
        ]
    },
    {
        "channel_name": "روتانا كيدز",
        "channel_logo": "https://media0101.elcinema.com/tvguide/1356_2.png",
        "programs": [
            {
                "name": "Bat Pat S2",
                "time": "01:00 صباحاً - 01:15 صباحاً",
                "type": "مسلسل - ﺭﺳﻮﻡ ﻣﺘﺤﺮﻛﺔ (2020)",
                "link": "https://elcinema.com/work/2084011/"
            },
            {
                "name": "Rob Dyrdek's Wild Grinders",
                "time": "01:15 صباحاً - 01:30 صباحاً",
                "type": "مسلسل (2012)",
                "link": "https://elcinema.com/work/2076191/"
            },
            {
                "name": "Gon",
                "time": "01:30 صباحاً - 01:45 صباحاً",
                "type": "مسلسل - ﺭﺳﻮﻡ ﻣﺘﺤﺮﻛﺔ (2012)",
                "link": "https://elcinema.com/work/2064804/"
            },
            {
                "name": "Boom & Reds",
                "time": "01:45 صباحاً - 02:00 صباحاً",
                "type": "مسلسل - ﺭﺳﻮﻡ ﻣﺘﺤﺮﻛﺔ (2006)",
                "link": "https://elcinema.com/work/2085648/"
            },
            {
                "name": "The Legend of Snow White",
                "time": "02:00 صباحاً - 02:30 صباحاً",
                "type": "مسلسل (1994)",
                "link": "https://elcinema.com/work/2054733/"
            },
            {
                "name": "AI Football GGO",
                "time": "02:30 صباحاً - 03:00 صباحاً",
                "type": "مسلسل (2010)",
                "link": "https://elcinema.com/work/2063570/"
            },
            {
                "name": "Robin Hood",
                "time": "03:00 صباحاً - 03:30 صباحاً",
                "type": "مسلسل - ﺭﺳﻮﻡ ﻣﺘﺤﺮﻛﺔ (1990)",
                "link": "https://elcinema.com/work/1727653/"
            }
        ]
    },
    {
        "channel_name": "إم بي سي مصر دراما",
        "channel_logo": "https://media0101.elcinema.com/tvguide/1399_2.png",
        "programs": [
            {
                "name": "الفرح فرحنا",
                "time": "12:30 صباحاً - 01:15 صباحاً",
                "type": "مسلسل (2022)",
                "link": "https://elcinema.com/work/2072480/"
            },
            {
                "name": "زلزال",
                "time": "01:15 صباحاً - 02:00 صباحاً",
                "type": "مسلسل (2019)",
                "link": "https://elcinema.com/work/2006065/"
            },
            {
                "name": "ذهاب وعودة",
                "time": "02:00 صباحاً - 02:45 صباحاً",
                "type": "مسلسل (2015)",
                "link": "https://elcinema.com/work/2033694/"
            },
            {
                "name": "كامل العدد +1",
                "time": "02:45 صباحاً - 03:45 صباحاً",
                "type": "مسلسل (2024)",
                "link": "https://elcinema.com/work/2083087/"
            }
        ]
    },
    {
        "channel_name": "أو إس إن شو كايس",
        "channel_logo": "https://media0101.elcinema.com/tvguide/1394_2.png",
        "programs": [
            {
                "name": "Rooster",
                "time": "01:00 صباحاً - 01:30 صباحاً",
                "type": "مسلسل (2026)",
                "link": "https://elcinema.com/work/2098700/"
            },
            {
                "name": "The Chair Company",
                "time": "01:30 صباحاً - 02:00 صباحاً",
                "type": "مسلسل (2025)",
                "link": "https://elcinema.com/work/2096736/"
            },
            {
                "name": "Ramy Youssef: More Feelings",
                "time": "02:00 صباحاً - 02:55 صباحاً",
                "type": "ﺑﺮﻧﺎﻣﺞ - ﺳﻬﺮﺓ ﺗﻠﻴﻔﺰﻳﻮﻧﻴﺔ (2024)",
                "link": "https://elcinema.com/work/2094585/"
            },
            {
                "name": "Bill Maher: Is Anyone Else Seeing This?",
                "time": "02:55 صباحاً - 04:00 صباحاً",
                "type": "ﺑﺮﻧﺎﻣﺞ - ﺳﻬﺮﺓ ﺗﻠﻴﻔﺰﻳﻮﻧﻴﺔ (2025)",
                "link": "https://elcinema.com/work/2093685/"
            }
        ]
    },
    {
        "channel_name": "ال دي سي",
        "channel_logo": "https://media0101.elcinema.com/tvguide/1246_2.png",
        "programs": [
            {
                "name": "وين كنتي ج1",
                "time": "12:30 صباحاً - 01:30 صباحاً",
                "type": "مسلسل (2016)",
                "link": "https://elcinema.com/work/2043599/"
            },
            {
                "name": "مش أنا",
                "time": "01:30 صباحاً - 02:15 صباحاً",
                "type": "مسلسل (2016)",
                "link": "https://elcinema.com/work/2043601/"
            },
            {
                "name": "تانغو",
                "time": "02:15 صباحاً - 03:00 صباحاً",
                "type": "مسلسل (2018)",
                "link": "https://elcinema.com/work/1198622/"
            },
            {
                "name": "نشرة الاخبار",
                "time": "03:00 صباحاً - 03:30 صباحاً",
                "type": "",
                "link": ""
            }
        ]
    },
    {
        "channel_name": "إل بي سي",
        "channel_logo": "https://media0101.elcinema.com/tvguide/1341_2.png",
        "programs": [
            {
                "name": "أهل الخطايا",
                "time": "01:00 صباحاً - 02:00 صباحاً",
                "type": "مسلسل (2025)",
                "link": "https://elcinema.com/work/2091891/"
            },
            {
                "name": "حفلة",
                "time": "02:00 صباحاً - 03:00 صباحاً",
                "type": "",
                "link": ""
            },
            {
                "name": "وردة شامية",
                "time": "03:00 صباحاً - 04:00 صباحاً",
                "type": "مسلسل (2017)",
                "link": "https://elcinema.com/work/2040083/"
            }
        ]
    },
    {
        "channel_name": "وان دراما",
        "channel_logo": "https://media0101.elcinema.com/tvguide/1405_2.png",
        "programs": [
            {
                "name": "The Pit S4",
                "time": "01:00 صباحاً - 02:00 صباحاً",
                "type": "مسلسل (2020)",
                "link": "https://elcinema.com/work/2067766/"
            },
            {
                "name": "Uzak Sehir",
                "time": "02:00 صباحاً - 02:30 صباحاً",
                "type": "مسلسل (2024)",
                "link": "https://elcinema.com/work/2091404/"
            },
            {
                "name": "Forbidden Love",
                "time": "02:30 صباحاً - 03:15 صباحاً",
                "type": "مسلسل (2008)",
                "link": "https://elcinema.com/work/1997628/"
            },
            {
                "name": "Establishment: Osman S1",
                "time": "03:15 صباحاً - 04:00 صباحاً",
                "type": "مسلسل (2019)",
                "link": "https://elcinema.com/work/2060082/"
            }
        ]
    },
    {
        "channel_name": "أو إس إن موفيز كوميدي",
        "channel_logo": "https://media0101.elcinema.com/tvguide/1231_2.png",
        "programs": [
            {
                "name": "The Disaster Artist",
                "time": "12:55 صباحاً - 02:35 صباحاً",
                "type": "فيلم (2017)",
                "link": "https://elcinema.com/work/2046441/"
            },
            {
                "name": "We're the Millers",
                "time": "02:35 صباحاً - 04:20 صباحاً",
                "type": "فيلم (2013)",
                "link": "https://elcinema.com/work/2022174/"
            }
        ]
    },
    {
        "channel_name": "أو إس إن فاميلي موفيز",
        "channel_logo": "https://media0101.elcinema.com/tvguide/1392_2.png",
        "programs": [
            {
                "name": "Harry Potter and the Chamber of Secrets",
                "time": "12:22 صباحاً - 02:59 صباحاً",
                "type": "فيلم (2002)",
                "link": "https://elcinema.com/work/2001203/"
            },
            {
                "name": "Megamind",
                "time": "02:59 صباحاً - 04:32 صباحاً",
                "type": "فيلم - ﺭﺳﻮﻡ ﻣﺘﺤﺮﻛﺔ (2010)",
                "link": "https://elcinema.com/work/1999942/"
            }
        ]
    },
    {
        "channel_name": "الشروق الجزائرية",
        "channel_logo": "https://media0101.elcinema.com/tvguide/1315_2.png",
        "programs": [
            {
                "name": "برنامج",
                "time": "01:00 صباحاً - 02:00 صباحاً",
                "type": "",
                "link": ""
            },
            {
                "name": "برنامج",
                "time": "02:00 صباحاً - 03:00 صباحاً",
                "type": "",
                "link": ""
            },
            {
                "name": "برنامج",
                "time": "03:00 صباحاً - 04:00 صباحاً",
                "type": "",
                "link": ""
            }
        ]
    },
    {
        "channel_name": "اﻹمارات",
        "channel_logo": "https://media0101.elcinema.com/tvguide/1135_2.png",
        "programs": [
            {
                "name": "برنامج وثائقي",
                "time": "12:30 صباحاً - 01:30 صباحاً",
                "type": "",
                "link": ""
            },
            {
                "name": "هيا الروح",
                "time": "01:30 صباحاً - 02:30 صباحاً",
                "type": "مسلسل (2022)",
                "link": "https://elcinema.com/work/2071315/"
            },
            {
                "name": "إللي نحبهم",
                "time": "02:30 صباحاً - 03:00 صباحاً",
                "type": "مسلسل (2021)",
                "link": "https://elcinema.com/work/2068428/"
            },
            {
                "name": "برنامج علوم الدار",
                "time": "03:00 صباحاً - 04:00 صباحاً",
                "type": "",
                "link": ""
            }
        ]
    },
    {
        "channel_name": "نايل دراما",
        "channel_logo": "https://media0101.elcinema.com/tvguide/1156_2.png",
        "programs": [
            {
                "name": "أرابيسك: أيام حسن النعماني",
                "time": "01:00 صباحاً - 02:00 صباحاً",
                "type": "مسلسل (1994)",
                "link": "https://elcinema.com/work/1010599/"
            },
            {
                "name": "الرقص على سلالم متحركة",
                "time": "02:00 صباحاً - 03:00 صباحاً",
                "type": "مسلسل (2001)",
                "link": "https://elcinema.com/work/1023193/"
            },
            {
                "name": "عائلة الحاج متولي",
                "time": "03:00 صباحاً - 04:00 صباحاً",
                "type": "مسلسل (2001)",
                "link": "https://elcinema.com/work/1028580/"
            }
        ]
    },
    {
        "channel_name": "أو إس إن ياهلا",
        "channel_logo": "https://media0101.elcinema.com/tvguide/1205_2.png",
        "programs": [
            {
                "name": "درب الذهب",
                "time": "12:30 صباحاً - 01:15 صباحاً",
                "type": "مسلسل (2026)",
                "link": "https://elcinema.com/work/2097838/"
            },
            {
                "name": "على قد الحب",
                "time": "01:15 صباحاً - 02:00 صباحاً",
                "type": "مسلسل (2026)",
                "link": "https://elcinema.com/work/2097692/"
            },
            {
                "name": "سعادة المجنون",
                "time": "02:00 صباحاً - 02:50 صباحاً",
                "type": "مسلسل (2026)",
                "link": "https://elcinema.com/work/2097143/"
            },
            {
                "name": "خطيئة أخيرة",
                "time": "02:50 صباحاً - 03:40 صباحاً",
                "type": "مسلسل (2025)",
                "link": "https://elcinema.com/work/2093055/"
            }
        ]
    },
    {
        "channel_name": "سي بي سي",
        "channel_logo": "https://media0101.elcinema.com/tvguide/1198_2.png",
        "programs": [
            {
                "name": "برغم القانون",
                "time": "01:00 صباحاً - 02:00 صباحاً",
                "type": "مسلسل (2024)",
                "link": "https://elcinema.com/work/2085904/"
            },
            {
                "name": "درش",
                "time": "02:00 صباحاً - 03:00 صباحاً",
                "type": "مسلسل (2026)",
                "link": "https://elcinema.com/work/2096819/"
            },
            {
                "name": "برنامج",
                "time": "03:00 صباحاً - 04:00 صباحاً",
                "type": "",
                "link": ""
            }
        ]
    },
    {
        "channel_name": "أو إس إن كرايم",
        "channel_logo": "https://media0101.elcinema.com/tvguide/1395_2.png",
        "programs": [
            {
                "name": "Dexter S2",
                "time": "12:25 صباحاً - 01:25 صباحاً",
                "type": "مسلسل (2007)",
                "link": "https://elcinema.com/work/2067947/"
            },
            {
                "name": "Dexter S2",
                "time": "01:25 صباحاً - 02:25 صباحاً",
                "type": "مسلسل (2007)",
                "link": "https://elcinema.com/work/2067947/"
            },
            {
                "name": "The Mentalist S1",
                "time": "02:25 صباحاً - 03:15 صباحاً",
                "type": "مسلسل (2008)",
                "link": "https://elcinema.com/work/2003783/"
            },
            {
                "name": "Blindspot S5",
                "time": "03:15 صباحاً - 04:00 صباحاً",
                "type": "مسلسل (2020)",
                "link": "https://elcinema.com/work/2060400/"
            }
        ]
    },
    {
        "channel_name": "العراقية",
        "channel_logo": "https://media0101.elcinema.com/tvguide/1349_2.png",
        "programs": [
            {
                "name": "برنامج",
                "time": "01:00 صباحاً - 02:00 صباحاً",
                "type": "",
                "link": ""
            },
            {
                "name": "برنامج معارف التراث",
                "time": "02:00 صباحاً - 03:00 صباحاً",
                "type": "",
                "link": ""
            },
            {
                "name": "فترة دينية",
                "time": "03:00 صباحاً - 04:00 صباحاً",
                "type": "",
                "link": ""
            }
        ]
    },
    {
        "channel_name": "القاهرة والناس",
        "channel_logo": "https://media0101.elcinema.com/tvguide/1174_2.png",
        "programs": [
            {
                "name": "وجوه",
                "time": "12:58 صباحاً - 01:52 صباحاً",
                "type": "مسلسل (2022)",
                "link": "https://elcinema.com/work/2073212/"
            },
            {
                "name": "الكاميرا الخفية",
                "time": "01:52 صباحاً - 02:00 صباحاً",
                "type": "ﺑﺮﻧﺎﻣﺞ (1991)",
                "link": "https://elcinema.com/work/2072816/"
            },
            {
                "name": "برنامج الدكتور",
                "time": "02:00 صباحاً - 04:15 صباحاً",
                "type": "",
                "link": ""
            }
        ]
    },
    {
        "channel_name": "إم بي سي بوليوود",
        "channel_logo": "https://media0101.elcinema.com/tvguide/1259_2.png",
        "programs": [
            {
                "name": "على صدى الخلخال",
                "time": "12:30 صباحاً - 01:30 صباحاً",
                "type": "مسلسل (2023)",
                "link": "https://elcinema.com/work/2094065/"
            },
            {
                "name": "Meri Zindagi Hai Tu",
                "time": "01:30 صباحاً - 02:15 صباحاً",
                "type": "مسلسل (2025)",
                "link": "https://elcinema.com/work/2099383/"
            },
            {
                "name": "Seher Hone Ko Hai",
                "time": "02:15 صباحاً - 03:00 صباحاً",
                "type": "مسلسل (2025)",
                "link": "https://elcinema.com/work/2099382/"
            },
            {
                "name": "Kaminey",
                "time": "03:00 صباحاً - 05:15 صباحاً",
                "type": "فيلم (2009)",
                "link": "https://elcinema.com/work/2026677/"
            }
        ]
    },
    {
        "channel_name": "نتورك بالعربية",
        "channel_logo": "https://media0101.elcinema.com/tvguide/1242_2.png",
        "programs": [
            {
                "name": "Regular Show S1",
                "time": "01:00 صباحاً - 02:00 صباحاً",
                "type": "مسلسل (2010)",
                "link": "https://elcinema.com/work/2026864/"
            },
            {
                "name": "Adventure Time with Finn & Jake",
                "time": "02:00 صباحاً - 03:00 صباحاً",
                "type": "مسلسل - ﺭﺳﻮﻡ ﻣﺘﺤﺮﻛﺔ (2010)",
                "link": "https://elcinema.com/work/2025581/"
            },
            {
                "name": "We Bare Bears S2",
                "time": "03:00 صباحاً - 04:00 صباحاً",
                "type": "مسلسل (2016)",
                "link": "https://elcinema.com/work/2063439/"
            }
        ]
    },
    {
        "channel_name": "رؤيا",
        "channel_logo": "https://media0101.elcinema.com/tvguide/1299_2.png",
        "programs": [
            {
                "name": "دنيا يا دنيا",
                "time": "12:30 صباحاً - 03:30 صباحاً",
                "type": "ﺑﺮﻧﺎﻣﺞ (2019)",
                "link": "https://elcinema.com/work/2051958/"
            }
        ]
    },
    {
        "channel_name": "وان موفيز",
        "channel_logo": "https://media0101.elcinema.com/tvguide/1404_2.png",
        "programs": [
            {
                "name": "Final Score",
                "time": "01:00 صباحاً - 03:00 صباحاً",
                "type": "فيلم (2017)",
                "link": "https://elcinema.com/work/2046137/"
            },
            {
                "name": "R.I.P.D.",
                "time": "03:00 صباحاً - 05:30 صباحاً",
                "type": "فيلم (2013)",
                "link": "https://elcinema.com/work/2006830/"
            }
        ]
    },
    {
        "channel_name": "أو إس إن ياهلا أفلام",
        "channel_logo": "https://media0101.elcinema.com/tvguide/1285_2.png",
        "programs": [
            {
                "name": "كيرة والجن",
                "time": "11:40 مساءً - 02:30 صباحاً",
                "type": "فيلم (2022)",
                "link": "https://elcinema.com/work/2058736/"
            },
            {
                "name": "Yellow Bus",
                "time": "02:30 صباحاً - 04:25 صباحاً",
                "type": "فيلم (2023)",
                "link": "https://elcinema.com/work/2084578/"
            }
        ]
    },
    {
        "channel_name": "ستار أكشن",
        "channel_logo": "https://media0101.elcinema.com/tvguide/1330_2.png",
        "programs": [
            {
                "name": "The Puppet Masters",
                "time": "12:55 صباحاً - 03:00 صباحاً",
                "type": "فيلم (1994)",
                "link": "https://elcinema.com/work/2097518/"
            },
            {
                "name": "Primeval",
                "time": "03:00 صباحاً - 04:35 صباحاً",
                "type": "فيلم (2007)",
                "link": "https://elcinema.com/work/2002423/"
            }
        ]
    },
    {
        "channel_name": "إم بي سي العراق",
        "channel_logo": "https://media0101.elcinema.com/tvguide/1340_2.png",
        "programs": [
            {
                "name": "درش",
                "time": "12:45 صباحاً - 01:30 صباحاً",
                "type": "مسلسل (2026)",
                "link": "https://elcinema.com/work/2096819/"
            },
            {
                "name": "أم أربعة وأربعين",
                "time": "01:30 صباحاً - 02:15 صباحاً",
                "type": "مسلسل (2025)",
                "link": "https://elcinema.com/work/2090986/"
            },
            {
                "name": "المتمرد",
                "time": "02:15 صباحاً - 03:00 صباحاً",
                "type": "مسلسل (2023)",
                "link": "https://elcinema.com/work/2078135/"
            },
            {
                "name": "عائلتي تربح",
                "time": "03:00 صباحاً - 04:00 صباحاً",
                "type": "ﺑﺮﻧﺎﻣﺞ (2019)",
                "link": "https://elcinema.com/work/2064319/"
            }
        ]
    },
    {
        "channel_name": "إم بي سي ماكس",
        "channel_logo": "https://media0101.elcinema.com/tvguide/1132_2.png",
        "programs": [
            {
                "name": "42",
                "time": "11:30 مساءً - 01:35 صباحاً",
                "type": "فيلم (2013)",
                "link": "https://elcinema.com/work/2018041/"
            },
            {
                "name": "Ghost in the Shell",
                "time": "01:35 صباحاً - 03:20 صباحاً",
                "type": "فيلم (2017)",
                "link": "https://elcinema.com/work/2043849/"
            },
            {
                "name": "Cloud Atlas",
                "time": "09:20  مساءً - 12:00  صباحًا",
                "type": "فيلم (2012)",
                "link": "https://elcinema.com/work/2005688/"
            }
        ]
    },
    {
        "channel_name": "ستار ورلد",
        "channel_logo": "https://media0101.elcinema.com/tvguide/1329_2.png",
        "programs": [
            {
                "name": "برنامج Jamie: Fast and Simple",
                "time": "12:30 صباحاً - 01:20 صباحاً",
                "type": "",
                "link": ""
            },
            {
                "name": "MasterChef Australia S15",
                "time": "01:20 صباحاً - 02:10 صباحاً",
                "type": "ﺑﺮﻧﺎﻣﺞ (2025)",
                "link": "https://elcinema.com/work/2017739/"
            },
            {
                "name": "Britain's Got Talent 14",
                "time": "02:10 صباحاً - 03:35 صباحاً",
                "type": "ﺑﺮﻧﺎﻣﺞ (2020)",
                "link": "https://elcinema.com/work/2066763/"
            }
        ]
    },
    {
        "channel_name": "الثانية",
        "channel_logo": "https://media0101.elcinema.com/tvguide/1398_2.png",
        "programs": [
            {
                "name": "بنات الباشا",
                "time": "01:00 صباحاً - 02:00 صباحاً",
                "type": "مسلسل (2025)",
                "link": "https://elcinema.com/work/2092606/"
            },
            {
                "name": "بنت النعمان",
                "time": "02:00 صباحاً - 03:00 صباحاً",
                "type": "مسلسل (2026)",
                "link": "https://elcinema.com/work/2097144/"
            },
            {
                "name": "برنامج",
                "time": "03:00 صباحاً - 04:00 صباحاً",
                "type": "",
                "link": ""
            }
        ]
    },
    {
        "channel_name": "أو إٍس إن ناو",
        "channel_logo": "https://media0101.elcinema.com/tvguide/1396_2.png",
        "programs": [
            {
                "name": "The Affair S3",
                "time": "12:55 صباحاً - 02:00 صباحاً",
                "type": "مسلسل (2016)",
                "link": "https://elcinema.com/work/2098091/"
            },
            {
                "name": "Below Deck S11",
                "time": "02:00 صباحاً - 03:00 صباحاً",
                "type": "مسلسل (2024)",
                "link": "https://elcinema.com/work/2094181/"
            },
            {
                "name": "The Carrie Diaries",
                "time": "03:00 صباحاً - 03:50 صباحاً",
                "type": "مسلسل (2013)",
                "link": "https://elcinema.com/work/2025556/"
            }
        ]
    },
    {
        "channel_name": "ماسبيرو زمان",
        "channel_logo": "https://media0101.elcinema.com/tvguide/1336_2.png",
        "programs": [
            {
                "name": "برنامج تاكسي السهرة",
                "time": "12:00 صباحاً - 01:30 صباحاً",
                "type": "",
                "link": ""
            },
            {
                "name": "حفل غنائي",
                "time": "01:30 صباحاً - 02:00 صباحاً",
                "type": "",
                "link": ""
            },
            {
                "name": "الحسن البصري",
                "time": "02:00 صباحاً - 03:00 صباحاً",
                "type": "مسلسل (2000)",
                "link": "https://elcinema.com/work/1766322/"
            },
            {
                "name": "العلم والإيمان",
                "time": "03:00 صباحاً - 03:30 صباحاً",
                "type": "ﺑﺮﻧﺎﻣﺞ (1971)",
                "link": "https://elcinema.com/work/2010135/"
            }
        ]
    },
    {
        "channel_name": "إم بي سي أكشن",
        "channel_logo": "https://media0101.elcinema.com/tvguide/1130_2.png",
        "programs": [
            {
                "name": "برنامج american ninja warrior",
                "time": "12:30 صباحاً - 01:30 صباحاً",
                "type": "",
                "link": ""
            },
            {
                "name": "The Promised Neverland",
                "time": "01:30 صباحاً - 02:00 صباحاً",
                "type": "مسلسل (2019)",
                "link": "https://elcinema.com/work/2093612/"
            },
            {
                "name": "برنامج action bodcast",
                "time": "02:00 صباحاً - 03:00 صباحاً",
                "type": "",
                "link": ""
            },
            {
                "name": "بودكاست ملح الدوري",
                "time": "03:00 صباحاً - 04:00 صباحاً",
                "type": "",
                "link": ""
            }
        ]
    },
    {
        "channel_name": "إل بي سي آي",
        "channel_logo": "https://media0101.elcinema.com/tvguide/1168_2.png",
        "programs": [
            {
                "name": "وين كنتي ج1",
                "time": "12:30 صباحاً - 01:30 صباحاً",
                "type": "مسلسل (2016)",
                "link": "https://elcinema.com/work/2043599/"
            },
            {
                "name": "مش أنا",
                "time": "01:30 صباحاً - 02:15 صباحاً",
                "type": "مسلسل (2016)",
                "link": "https://elcinema.com/work/2043601/"
            },
            {
                "name": "تانغو",
                "time": "02:15 صباحاً - 03:00 صباحاً",
                "type": "مسلسل (2018)",
                "link": "https://elcinema.com/work/1198622/"
            },
            {
                "name": "نشرة الاخبار",
                "time": "03:00 صباحاً - 03:30 صباحاً",
                "type": "",
                "link": ""
            }
        ]
    },
    {
        "channel_name": "ميكس بالعربي",
        "channel_logo": "https://media0101.elcinema.com/tvguide/1371_2.png",
        "programs": [
            {
                "name": "فيلم",
                "time": "12:00 صباحاً - 02:00 صباحاً",
                "type": "",
                "link": ""
            },
            {
                "name": "Forbidden Apple S4",
                "time": "02:00 صباحاً - 03:00 صباحاً",
                "type": "مسلسل (2020)",
                "link": "https://elcinema.com/work/2077592/"
            },
            {
                "name": "جبل الحلال",
                "time": "03:00 صباحاً - 04:00 صباحاً",
                "type": "مسلسل (2014)",
                "link": "https://elcinema.com/work/2025549/"
            }
        ]
    },
    {
        "channel_name": "نايل لايف",
        "channel_logo": "https://media0101.elcinema.com/tvguide/1159_2.png",
        "programs": [
            {
                "name": "فيلم",
                "time": "12:00 صباحاً - 02:00 صباحاً",
                "type": "",
                "link": ""
            },
            {
                "name": "رأفت الهجان ج1",
                "time": "02:00 صباحاً - 03:00 صباحاً",
                "type": "مسلسل (1988)",
                "link": "https://elcinema.com/work/1011599/"
            },
            {
                "name": "برنامج الحريف",
                "time": "03:00 صباحاً - 04:00 صباحاً",
                "type": "",
                "link": ""
            }
        ]
    },
    {
        "channel_name": "أو إس إن ياهلا بالعربي",
        "channel_logo": "https://media0101.elcinema.com/tvguide/1390_2.png",
        "programs": [
            {
                "name": "Senden Daha Güzel",
                "time": "12:20 صباحاً - 01:15 صباحاً",
                "type": "مسلسل (2022)",
                "link": "https://elcinema.com/work/2089137/"
            },
            {
                "name": "Forbidden Apple S3",
                "time": "01:15 صباحاً - 02:00 صباحاً",
                "type": "مسلسل (2019)",
                "link": "https://elcinema.com/work/2083254/"
            },
            {
                "name": "Succession",
                "time": "02:00 صباحاً - 03:00 صباحاً",
                "type": "مسلسل (2018)",
                "link": "https://elcinema.com/work/2053601/"
            },
            {
                "name": "Succession",
                "time": "03:00 صباحاً - 04:00 صباحاً",
                "type": "مسلسل (2018)",
                "link": "https://elcinema.com/work/2053601/"
            }
        ]
    },
    {
        "channel_name": "سي بي سي سفرة",
        "channel_logo": "https://media0101.elcinema.com/tvguide/1260_2.png",
        "programs": [
            {
                "name": "برنامج الشيف",
                "time": "12:00 صباحاً - 01:30 صباحاً",
                "type": "",
                "link": ""
            },
            {
                "name": "أميرة في المطبخ",
                "time": "01:30 صباحاً - 02:30 صباحاً",
                "type": "ﺑﺮﻧﺎﻣﺞ (2011)",
                "link": "https://elcinema.com/work/2032096/"
            },
            {
                "name": "برنامج عمايل إيديا",
                "time": "02:30 صباحاً - 03:00 صباحاً",
                "type": "",
                "link": ""
            },
            {
                "name": "برنامج بالهنا والشفا",
                "time": "03:00 صباحاً - 04:00 صباحاً",
                "type": "",
                "link": ""
            }
        ]
    },
    {
        "channel_name": "أون إي",
        "channel_logo": "https://media0101.elcinema.com/tvguide/1203_2.png",
        "programs": [
            {
                "name": "فيلم عربي",
                "time": "12:00 صباحاً - 02:00 صباحاً",
                "type": "",
                "link": ""
            },
            {
                "name": "برنامج",
                "time": "02:00 صباحاً - 03:00 صباحاً",
                "type": "",
                "link": ""
            },
            {
                "name": "برنامج",
                "time": "03:00 صباحاً - 04:00 صباحاً",
                "type": "",
                "link": ""
            }
        ]
    },
    {
        "channel_name": "سيما",
        "channel_logo": "https://media0101.elcinema.com/tvguide/1176_2.png",
        "programs": [
            {
                "name": "الصاغة",
                "time": "01:00 صباحاً - 03:00 صباحاً",
                "type": "فيلم (1994)",
                "link": "https://elcinema.com/work/1003861/"
            },
            {
                "name": "قمر ١٤",
                "time": "03:00 صباحاً - 05:00 صباحاً",
                "type": "فيلم (1950)",
                "link": "https://elcinema.com/work/1006960/"
            }
        ]
    },
    {
        "channel_name": "دي إم سي",
        "channel_logo": "https://media0101.elcinema.com/tvguide/1290_2.png",
        "programs": [
            {
                "name": "زينهم",
                "time": "12:30 صباحاً - 01:35 صباحاً",
                "type": "مسلسل (2023)",
                "link": "https://elcinema.com/work/2082777/"
            },
            {
                "name": "اتنين غيرنا",
                "time": "01:35 صباحاً - 03:45 صباحاً",
                "type": "مسلسل (2026)",
                "link": "https://elcinema.com/work/2096453/"
            }
        ]
    },
    {
        "channel_name": "إيه تي في",
        "channel_logo": "https://media0101.elcinema.com/tvguide/1380_2.png",
        "programs": [
            {
                "name": "مدينة الرياح",
                "time": "01:00 صباحاً - 01:35 صباحاً",
                "type": "مسلسل (1988)",
                "link": "https://elcinema.com/work/1998142/"
            },
            {
                "name": "ألو جميل ألو هناء",
                "time": "01:35 صباحاً - 02:30 صباحاً",
                "type": "مسلسل (2001)",
                "link": "https://elcinema.com/work/1798409/"
            },
            {
                "name": "درب الزلق",
                "time": "02:30 صباحاً - 03:10 صباحاً",
                "type": "مسلسل (1977)",
                "link": "https://elcinema.com/work/1037220/"
            },
            {
                "name": "مرايا 2003",
                "time": "03:10 صباحاً - 03:50 صباحاً",
                "type": "مسلسل (2003)",
                "link": "https://elcinema.com/work/1365904/"
            }
        ]
    },
    {
        "channel_name": "روتانا دراما",
        "channel_logo": "https://media0101.elcinema.com/tvguide/1147_2.png",
        "programs": [
            {
                "name": "قلبي ومفتاحه",
                "time": "01:00 صباحاً - 02:00 صباحاً",
                "type": "مسلسل (2025)",
                "link": "https://elcinema.com/work/2090977/"
            },
            {
                "name": "وتقابل حبيب",
                "time": "02:00 صباحاً - 03:00 صباحاً",
                "type": "مسلسل (2025)",
                "link": "https://elcinema.com/work/2089079/"
            },
            {
                "name": "من الأحد إلى الخميس",
                "time": "03:00 صباحاً - 04:00 صباحاً",
                "type": "مسلسل (2025)",
                "link": "https://elcinema.com/work/2088639/"
            }
        ]
    },
    {
        "channel_name": "الوطنية 2",
        "channel_logo": "https://media0101.elcinema.com/tvguide/1334_2.png",
        "programs": [
            {
                "name": "تقطيع .. ترييش .. وخدمات أخرى",
                "time": "11:55 مساءً - 02:00 صباحاً",
                "type": "مسلسل - ﺳﻴﺖ ﻛﻮﻡ",
                "link": "https://elcinema.com/work/2050901/"
            },
            {
                "name": "برنامج",
                "time": "02:00 صباحاً - 04:00 صباحاً",
                "type": "",
                "link": ""
            }
        ]
    },
    {
        "channel_name": "صدى البلد دراما",
        "channel_logo": "https://media0101.elcinema.com/tvguide/1227_2.png",
        "programs": [
            {
                "name": "بيت الشدة",
                "time": "01:00 صباحاً - 02:00 صباحاً",
                "type": "مسلسل (2022)",
                "link": "https://elcinema.com/work/2073124/"
            },
            {
                "name": "بـ١٠٠ راجل",
                "time": "02:00 صباحاً - 03:00 صباحاً",
                "type": "مسلسل (2024)",
                "link": "https://elcinema.com/work/2083079/"
            },
            {
                "name": "العربجي",
                "time": "03:00 صباحاً - 04:00 صباحاً",
                "type": "مسلسل (2023)",
                "link": "https://elcinema.com/work/2060447/"
            }
        ]
    },
    {
        "channel_name": "دجلة",
        "channel_logo": "https://media0101.elcinema.com/tvguide/1385_2.png",
        "programs": [
            {
                "name": "برنامج صباح دجلة",
                "time": "12:00 صباحاً - 02:00 صباحاً",
                "type": "",
                "link": ""
            },
            {
                "name": "برنامج حرير",
                "time": "02:00 صباحاً - 03:00 صباحاً",
                "type": "",
                "link": ""
            },
            {
                "name": "برنامج منا وبينا",
                "time": "03:00 صباحاً - 04:00 صباحاً",
                "type": "",
                "link": ""
            }
        ]
    },
    {
        "channel_name": "تن",
        "channel_logo": "https://media0101.elcinema.com/tvguide/1280_2.png",
        "programs": [
            {
                "name": "برنامج لايف ستايل",
                "time": "01:00 صباحاً - 02:00 صباحاً",
                "type": "",
                "link": ""
            },
            {
                "name": "برنامج من قلب الصعيد",
                "time": "02:00 صباحاً - 03:00 صباحاً",
                "type": "",
                "link": ""
            },
            {
                "name": "ريا وسكينة",
                "time": "03:00 صباحاً - 04:00 صباحاً",
                "type": "مسلسل (2005)",
                "link": "https://elcinema.com/work/1326791/"
            }
        ]
    },
    {
        "channel_name": "روتانا كلاسيك",
        "channel_logo": "https://media0101.elcinema.com/tvguide/1217_2.png",
        "programs": [
            {
                "name": "احترس من الخط",
                "time": "11:00 مساءً - 01:30 صباحاً",
                "type": "فيلم (1984)",
                "link": "https://elcinema.com/work/1007442/"
            },
            {
                "name": "أغاني من حفلات قديمة",
                "time": "01:30 صباحاً - 02:00 صباحاً",
                "type": "",
                "link": ""
            },
            {
                "name": "حفل أم كلثوم",
                "time": "02:00 صباحاً - 03:00 صباحاً",
                "type": "",
                "link": ""
            },
            {
                "name": "قطار الليل",
                "time": "03:00 صباحاً - 05:00 صباحاً",
                "type": "فيلم (1953)",
                "link": "https://elcinema.com/work/1006488/"
            }
        ]
    },
    {
        "channel_name": "عَمان",
        "channel_logo": "https://media0101.elcinema.com/tvguide/1298_2.png",
        "programs": [
            {
                "name": "Payitaht: Abdülhamid",
                "time": "12:35 صباحاً - 01:30 صباحاً",
                "type": "مسلسل (2017)",
                "link": "https://elcinema.com/work/2047805/"
            },
            {
                "name": "برنامج صحتين وهنا",
                "time": "01:30 صباحاً - 02:30 صباحاً",
                "type": "",
                "link": ""
            },
            {
                "name": "برنامج سلام الروح",
                "time": "02:30 صباحاً - 03:00 صباحاً",
                "type": "",
                "link": ""
            },
            {
                "name": "فترة دينية",
                "time": "03:00 صباحاً - 04:30 صباحاً",
                "type": "",
                "link": ""
            }
        ]
    },
    {
        "channel_name": "أو إس إن موفيز أكشن",
        "channel_logo": "https://media0101.elcinema.com/tvguide/1211_2.png",
        "programs": [
            {
                "name": "The Black Dahlia",
                "time": "11:10 مساءً - 01:20 صباحاً",
                "type": "فيلم (2006)",
                "link": "https://elcinema.com/work/2002563/"
            },
            {
                "name": "San Andreas",
                "time": "01:20 صباحاً - 03:30 صباحاً",
                "type": "فيلم (2015)",
                "link": "https://elcinema.com/work/2035161/"
            }
        ]
    },
    {
        "channel_name": "أو إس إن وان",
        "channel_logo": "https://media0101.elcinema.com/tvguide/1393_2.png",
        "programs": [
            {
                "name": "Watching You",
                "time": "12:45 صباحاً - 01:40 صباحاً",
                "type": "مسلسل (2025)",
                "link": "https://elcinema.com/work/2096647/"
            },
            {
                "name": "Apples Never Fall",
                "time": "01:40 صباحاً - 02:35 صباحاً",
                "type": "مسلسل (2024)",
                "link": "https://elcinema.com/work/2083906/"
            },
            {
                "name": "Superman & Lois S2",
                "time": "02:35 صباحاً - 03:20 صباحاً",
                "type": "مسلسل (2022)",
                "link": "https://elcinema.com/work/2072877/"
            },
            {
                "name": "Superman & Lois S2",
                "time": "03:20 صباحاً - 04:05 صباحاً",
                "type": "مسلسل (2022)",
                "link": "https://elcinema.com/work/2072877/"
            }
        ]
    },
    {
        "channel_name": "إم بي سي",
        "channel_logo": "https://media0101.elcinema.com/tvguide/1127_2.png",
        "programs": [
            {
                "name": "برنامج على طاولة منى",
                "time": "12:30 صباحاً - 01:25 صباحاً",
                "type": "",
                "link": ""
            },
            {
                "name": "مطبخ المدينة",
                "time": "01:25 صباحاً - 02:15 صباحاً",
                "type": "مسلسل (2026)",
                "link": "https://elcinema.com/work/2097216/"
            },
            {
                "name": "درش",
                "time": "02:15 صباحاً - 03:00 صباحاً",
                "type": "مسلسل (2026)",
                "link": "https://elcinema.com/work/2096819/"
            },
            {
                "name": "ليل",
                "time": "03:00 صباحاً - 03:48 صباحاً",
                "type": "مسلسل (2025)",
                "link": "https://elcinema.com/work/2097384/"
            }
        ]
    },
    {
        "channel_name": "إس بي سي",
        "channel_logo": "https://media0101.elcinema.com/tvguide/1297_2.png",
        "programs": [
            {
                "name": "برنامج جو السعودية",
                "time": "01:00 صباحاً - 01:30 صباحاً",
                "type": "",
                "link": ""
            },
            {
                "name": "برنامج موسيقاتنا",
                "time": "01:30 صباحاً - 02:00 صباحاً",
                "type": "",
                "link": ""
            },
            {
                "name": "الناموس",
                "time": "02:00 صباحاً - 03:00 صباحاً",
                "type": "مسلسل (2021)",
                "link": "https://elcinema.com/work/2067377/"
            },
            {
                "name": "الكندوش",
                "time": "03:00 صباحاً - 04:00 صباحاً",
                "type": "",
                "link": ""
            }
        ]
    },
    {
        "channel_name": "نسمة",
        "channel_logo": "https://media0101.elcinema.com/tvguide/1304_2.png",
        "programs": [
            {
                "name": "يوسف الصديق",
                "time": "12:45 صباحاً - 01:30 صباحاً",
                "type": "مسلسل (2009)",
                "link": "https://elcinema.com/work/2001287/"
            },
            {
                "name": "برنامج البازار",
                "time": "01:30 صباحاً - 03:45 صباحاً",
                "type": "",
                "link": ""
            }
        ]
    },
    {
        "channel_name": "إم بي سي 3",
        "channel_logo": "https://media0101.elcinema.com/tvguide/1241_2.png",
        "programs": [
            {
                "name": "جوني جيتبوي",
                "time": "01:00 صباحاً - 01:30 صباحاً",
                "type": "مسلسل (2024)",
                "link": "https://elcinema.com/work/2099375/"
            },
            {
                "name": "Rugrats",
                "time": "01:30 صباحاً - 02:00 صباحاً",
                "type": "مسلسل - ﺭﺳﻮﻡ ﻣﺘﺤﺮﻛﺔ (1991)",
                "link": "https://elcinema.com/work/1061395/"
            },
            {
                "name": "Miraculous: Tales of Ladybug & Cat Noir S5",
                "time": "02:00 صباحاً - 02:30 صباحاً",
                "type": "مسلسل - ﺭﺳﻮﻡ ﻣﺘﺤﺮﻛﺔ (2022)",
                "link": "https://elcinema.com/work/2077300/"
            },
            {
                "name": "Teenage Mutant Ninja Turtles S1",
                "time": "02:30 صباحاً - 03:00 صباحاً",
                "type": "مسلسل (1987)",
                "link": "https://elcinema.com/work/2018938/"
            },
            {
                "name": "Star Trek: Prodigy",
                "time": "03:00 صباحاً - 03:30 صباحاً",
                "type": "مسلسل (2021)",
                "link": "https://elcinema.com/work/2091675/"
            }
        ]
    },
    {
        "channel_name": "الفجيرة",
        "channel_logo": "https://media0101.elcinema.com/tvguide/1302_2.png",
        "programs": [
            {
                "name": "بياعة النخي",
                "time": "01:00 صباحاً - 02:00 صباحاً",
                "type": "مسلسل (2016)",
                "link": "https://elcinema.com/work/1027603/"
            },
            {
                "name": "حب بين السطور",
                "time": "02:00 صباحاً - 03:00 صباحاً",
                "type": "مسلسل (2023)",
                "link": "https://elcinema.com/work/2079433/"
            },
            {
                "name": "روج أسود",
                "time": "03:00 صباحاً - 04:00 صباحاً",
                "type": "مسلسل (2026)",
                "link": "https://elcinema.com/work/2093113/"
            }
        ]
    },
    {
        "channel_name": "دي إم سي دراما",
        "channel_logo": "https://media0101.elcinema.com/tvguide/1292_2.png",
        "programs": [
            {
                "name": "الكبير أوي ج6",
                "time": "01:00 صباحاً - 02:00 صباحاً",
                "type": "مسلسل (2022)",
                "link": "https://elcinema.com/work/2072812/"
            },
            {
                "name": "ونحب تاني ليه",
                "time": "02:00 صباحاً - 03:00 صباحاً",
                "type": "مسلسل (2020)",
                "link": "https://elcinema.com/work/2059688/"
            },
            {
                "name": "نصيبي وقسمتك 3",
                "time": "03:00 صباحاً - 04:00 صباحاً",
                "type": "مسلسل (2019)",
                "link": "https://elcinema.com/work/2058571/"
            }
        ]
    },
    {
        "channel_name": "السعودية",
        "channel_logo": "https://media0101.elcinema.com/tvguide/1352_2.png",
        "programs": [
            {
                "name": "برنامج",
                "time": "01:00 صباحاً - 02:00 صباحاً",
                "type": "",
                "link": ""
            },
            {
                "name": "برنامج دورينا غير",
                "time": "02:00 صباحاً - 03:30 صباحاً",
                "type": "",
                "link": ""
            }
        ]
    },
    {
        "channel_name": "قناة مصر الأولى",
        "channel_logo": "https://media0101.elcinema.com/tvguide/1101_2.png",
        "programs": [
            {
                "name": "برنامج",
                "time": "01:00 صباحاً - 02:00 صباحاً",
                "type": "",
                "link": ""
            },
            {
                "name": "برنامج",
                "time": "02:00 صباحاً - 03:00 صباحاً",
                "type": "",
                "link": ""
            },
            {
                "name": "برنامج",
                "time": "03:00 صباحاً - 04:00 صباحاً",
                "type": "",
                "link": ""
            }
        ]
    },
    {
        "channel_name": "بي إن سيريس",
        "channel_logo": "https://media0101.elcinema.com/tvguide/1327_2.png",
        "programs": [
            {
                "name": "Outlander S2",
                "time": "01:00 صباحاً - 02:00 صباحاً",
                "type": "مسلسل (2016)",
                "link": "https://elcinema.com/work/2058283/"
            },
            {
                "name": "Landman S2",
                "time": "02:00 صباحاً - 03:00 صباحاً",
                "type": "مسلسل (2025)",
                "link": "https://elcinema.com/work/2096752/"
            },
            {
                "name": "The Lady",
                "time": "03:00 صباحاً - 04:00 صباحاً",
                "type": "مسلسل (2026)",
                "link": "https://elcinema.com/work/2099287/"
            }
        ]
    },
    {
        "channel_name": "النهار دراما",
        "channel_logo": "https://media0101.elcinema.com/tvguide/1223_2.png",
        "programs": [
            {
                "name": "كيد الحموات",
                "time": "01:00 صباحاً - 02:00 صباحاً",
                "type": "مسلسل (2014)",
                "link": "https://elcinema.com/work/2027423/"
            },
            {
                "name": "كيد الحموات",
                "time": "02:00 صباحاً - 03:00 صباحاً",
                "type": "مسلسل (2014)",
                "link": "https://elcinema.com/work/2027423/"
            },
            {
                "name": "بابا المجال",
                "time": "03:00 صباحاً - 04:00 صباحاً",
                "type": "مسلسل (2023)",
                "link": "https://elcinema.com/work/2076957/"
            }
        ]
    },
    {
        "channel_name": "إم تي في",
        "channel_logo": "https://media0101.elcinema.com/tvguide/1296_2.png",
        "programs": [
            {
                "name": "برنامج",
                "time": "01:00 صباحاً - 02:00 صباحاً",
                "type": "",
                "link": ""
            },
            {
                "name": "برنامج",
                "time": "02:00 صباحاً - 03:00 صباحاً",
                "type": "",
                "link": ""
            },
            {
                "name": "برنامج",
                "time": "03:00 صباحاً - 04:00 صباحاً",
                "type": "",
                "link": ""
            }
        ]
    },
    {
        "channel_name": "إم بي سي 5",
        "channel_logo": "https://media0101.elcinema.com/tvguide/1354_2.png",
        "programs": [
            {
                "name": "برنامج براد و صينية",
                "time": "12:30 صباحاً - 01:30 صباحاً",
                "type": "",
                "link": ""
            },
            {
                "name": "ولاد العم",
                "time": "01:30 صباحاً - 02:30 صباحاً",
                "type": "مسلسل (2021)",
                "link": "https://elcinema.com/work/2068527/"
            },
            {
                "name": "بين لقصور",
                "time": "02:30 صباحاً - 03:30 صباحاً",
                "type": "مسلسل (2024)",
                "link": "https://elcinema.com/work/2084334/"
            }
        ]
    },
    {
        "channel_name": "أو إس إن كوميدي",
        "channel_logo": "https://media0101.elcinema.com/tvguide/1257_2.png",
        "programs": [
            {
                "name": "Friends S7",
                "time": "12:50 صباحاً - 01:15 صباحاً",
                "type": "مسلسل - ﺳﻴﺖ ﻛﻮﻡ (2000)",
                "link": "https://elcinema.com/work/2061884/"
            },
            {
                "name": "Two and a Half Men S4",
                "time": "01:15 صباحاً - 01:35 صباحاً",
                "type": "مسلسل - ﺳﻴﺖ ﻛﻮﻡ (2006)",
                "link": "https://elcinema.com/work/2062275/"
            },
            {
                "name": "Two and a Half Men S4",
                "time": "01:35 صباحاً - 02:00 صباحاً",
                "type": "مسلسل - ﺳﻴﺖ ﻛﻮﻡ (2006)",
                "link": "https://elcinema.com/work/2062275/"
            },
            {
                "name": "Schitt's Creek S3",
                "time": "02:00 صباحاً - 02:20 صباحاً",
                "type": "مسلسل (2017)",
                "link": "https://elcinema.com/work/2083337/"
            },
            {
                "name": "Romantic Getaway",
                "time": "02:20 صباحاً - 02:50 صباحاً",
                "type": "مسلسل (2023)",
                "link": "https://elcinema.com/work/2083233/"
            },
            {
                "name": "St. Denis Medical S2",
                "time": "02:50 صباحاً - 03:15 صباحاً",
                "type": "مسلسل (2025)",
                "link": "https://elcinema.com/work/2097087/"
            },
            {
                "name": "Two and a Half Men S4",
                "time": "03:15 صباحاً - 03:40 صباحاً",
                "type": "مسلسل - ﺳﻴﺖ ﻛﻮﻡ (2006)",
                "link": "https://elcinema.com/work/2062275/"
            }
        ]
    },
    {
        "channel_name": "ميكس",
        "channel_logo": "https://media0101.elcinema.com/tvguide/1355_2.png",
        "programs": [
            {
                "name": "Jeepers Creepers 2",
                "time": "12:00 صباحاً - 01:45 صباحاً",
                "type": "فيلم (2003)",
                "link": "https://elcinema.com/work/2002104/"
            },
            {
                "name": "Top Gun",
                "time": "01:45 صباحاً - 03:45 صباحاً",
                "type": "فيلم (1986)",
                "link": "https://elcinema.com/work/2001057/"
            }
        ]
    },
    {
        "channel_name": "دبي زمان",
        "channel_logo": "https://media0101.elcinema.com/tvguide/1283_2.png",
        "programs": [
            {
                "name": "برنامج",
                "time": "01:00 صباحاً - 02:00 صباحاً",
                "type": "",
                "link": ""
            },
            {
                "name": "وداعا يا ربيع العمر",
                "time": "02:00 صباحاً - 03:00 صباحاً",
                "type": "مسلسل (1991)",
                "link": "https://elcinema.com/work/2020203/"
            },
            {
                "name": "برنامج وجوه عربية",
                "time": "03:00 صباحاً - 04:00 صباحاً",
                "type": "",
                "link": ""
            }
        ]
    },
    {
        "channel_name": "الشارقة",
        "channel_logo": "https://media0101.elcinema.com/tvguide/1188_2.png",
        "programs": [
            {
                "name": "برنامج",
                "time": "01:00 صباحاً - 02:00 صباحاً",
                "type": "",
                "link": ""
            },
            {
                "name": "برنامج",
                "time": "02:00 صباحاً - 03:00 صباحاً",
                "type": "",
                "link": ""
            },
            {
                "name": "برنامج عباد الرحمن",
                "time": "03:00 صباحاً - 03:20 صباحاً",
                "type": "",
                "link": ""
            },
            {
                "name": "برنامج نصيحة طبيب",
                "time": "03:20 صباحاً - 03:30 صباحاً",
                "type": "",
                "link": ""
            }
        ]
    },
    {
        "channel_name": "الرشيد",
        "channel_logo": "https://media0101.elcinema.com/tvguide/1306_2.png",
        "programs": [
            {
                "name": "برنامج",
                "time": "01:00 صباحاً - 02:00 صباحاً",
                "type": "",
                "link": ""
            },
            {
                "name": "برنامج",
                "time": "02:00 صباحاً - 03:00 صباحاً",
                "type": "",
                "link": ""
            },
            {
                "name": "برنامج",
                "time": "03:00 صباحاً - 04:00 صباحاً",
                "type": "",
                "link": ""
            }
        ]
    },
    {
        "channel_name": "إم بي سي دراما +",
        "channel_logo": "https://media0101.elcinema.com/tvguide/1131_2.png",
        "programs": [
            {
                "name": "Golden Boy",
                "time": "01:00 صباحاً - 01:45 صباحاً",
                "type": "مسلسل (2022)",
                "link": "https://elcinema.com/work/2076511/"
            },
            {
                "name": "Parineetii",
                "time": "01:45 صباحاً - 02:30 صباحاً",
                "type": "مسلسل (2022)",
                "link": "https://elcinema.com/work/2091668/"
            },
            {
                "name": "ضرغام",
                "time": "02:30 صباحاً - 03:15 صباحاً",
                "type": "مسلسل (2025)",
                "link": "https://elcinema.com/work/2096593/"
            },
            {
                "name": "بيبي",
                "time": "03:15 صباحاً - 04:00 صباحاً",
                "type": "مسلسل (2022)",
                "link": "https://elcinema.com/work/2070924/"
            }
        ]
    },
    {
        "channel_name": "ناشيونال جيوجرافيك",
        "channel_logo": "https://media0101.elcinema.com/tvguide/1275_2.png",
        "programs": [
            {
                "name": "برنامج وحدة إنقاذ السيارات",
                "time": "01:00 صباحاً - 01:45 صباحاً",
                "type": "",
                "link": ""
            },
            {
                "name": "برنامج وحدة إنقاذ السيارات",
                "time": "01:45 صباحاً - 02:30 صباحاً",
                "type": "",
                "link": ""
            },
            {
                "name": "برنامج أساليب البقاء",
                "time": "02:30 صباحاً - 03:15 صباحاً",
                "type": "",
                "link": ""
            },
            {
                "name": "برنامج أساليب البقاء",
                "time": "03:15 صباحاً - 04:00 صباحاً",
                "type": "",
                "link": ""
            }
        ]
    },
    {
        "channel_name": "السعيدة",
        "channel_logo": "https://media0101.elcinema.com/tvguide/1339_2.png",
        "programs": [
            {
                "name": "برنامج",
                "time": "01:00 صباحاً - 02:00 صباحاً",
                "type": "",
                "link": ""
            },
            {
                "name": "برنامج",
                "time": "02:00 صباحاً - 03:00 صباحاً",
                "type": "",
                "link": ""
            },
            {
                "name": "برنامج",
                "time": "03:00 صباحاً - 04:00 صباحاً",
                "type": "",
                "link": ""
            }
        ]
    }
]