[
    {
        "channel_name": "المحور",
        "channel_logo": "https://media0101.elcinema.com/tvguide/1145_2.png",
        "programs": [
            {
                "name": "مسار إجباري",
                "time": "08:00 AM - 08:30 AM",
                "type": "مسلسل (2024)",
                "link": "https://elcinema.com/work/2083081/"
            },
            {
                "name": "برنامج الحياة أخلاق",
                "time": "08:30 AM - 09:30 AM",
                "type": "",
                "link": ""
            },
            {
                "name": "برنامج نبض الحياة",
                "time": "09:30 AM - 10:00 AM",
                "type": "",
                "link": ""
            },
            {
                "name": "برنامج اللعيبة",
                "time": "10:00 AM - 11:00 AM",
                "type": "",
                "link": ""
            }
        ]
    },
    {
        "channel_name": "الشرقية",
        "channel_logo": "https://media0101.elcinema.com/tvguide/1269_2.png",
        "programs": [
            {
                "name": "برنامج",
                "time": "08:00 AM - 09:00 AM",
                "type": "",
                "link": ""
            },
            {
                "name": "برنامج",
                "time": "09:00 AM - 10:10 AM",
                "type": "",
                "link": ""
            },
            {
                "name": "برنامج",
                "time": "10:10 AM - 11:00 AM",
                "type": "",
                "link": ""
            }
        ]
    },
    {
        "channel_name": "إم بي سي 2",
        "channel_logo": "https://media0101.elcinema.com/tvguide/1128_2.png",
        "programs": [
            {
                "name": "Come Away",
                "time": "08:00 AM - 10:00 AM",
                "type": "فيلم (2020)",
                "link": "https://elcinema.com/work/2061153/"
            },
            {
                "name": "The Losers",
                "time": "10:00 AM - 12:00 PM",
                "type": "فيلم (2010)",
                "link": "https://elcinema.com/work/1973271/"
            }
        ]
    },
    {
        "channel_name": "صدى البلد",
        "channel_logo": "https://media0101.elcinema.com/tvguide/1226_2.png",
        "programs": [
            {
                "name": "بـ١٠٠ راجل",
                "time": "08:00 AM - 09:00 AM",
                "type": "مسلسل (2024)",
                "link": "https://elcinema.com/work/2083079/"
            },
            {
                "name": "برنامج أنا وهو وهي",
                "time": "09:00 AM - 11:00 AM",
                "type": "",
                "link": ""
            }
        ]
    },
    {
        "channel_name": "أبو ظبي",
        "channel_logo": "https://media0101.elcinema.com/tvguide/1136_2.png",
        "programs": [
            {
                "name": "بيت أهلي",
                "time": "08:00 AM - 09:00 AM",
                "type": "مسلسل (2024)",
                "link": "https://elcinema.com/work/2083725/"
            },
            {
                "name": "أبو العروسة",
                "time": "09:00 AM - 10:00 AM",
                "type": "مسلسل (2017)",
                "link": "https://elcinema.com/work/2049280/"
            },
            {
                "name": "نشرة الاخبار",
                "time": "10:00 AM - 11:00 AM",
                "type": "",
                "link": ""
            }
        ]
    },
    {
        "channel_name": "عمان",
        "channel_logo": "https://media0101.elcinema.com/tvguide/1317_2.png",
        "programs": [
            {
                "name": "قصص الآيات في القرآن",
                "time": "07:50 AM - 08:15 AM",
                "type": "مسلسل (2015)",
                "link": "https://elcinema.com/work/2037208/"
            },
            {
                "name": "قنديل الحكايات ج1",
                "time": "08:15 AM - 08:30 AM",
                "type": "مسلسل (2020)",
                "link": "https://elcinema.com/work/2064090/"
            },
            {
                "name": "",
                "time": "08:30 AM - 08:45 AM",
                "type": "",
                "link": ""
            },
            {
                "name": "مسلسل الاطفال - الرحلة الى مكارم الاخلاق",
                "time": "08:45 AM - 09:00 AM",
                "type": "",
                "link": ""
            },
            {
                "name": "أخبار عمان",
                "time": "09:00 AM - 09:30 AM",
                "type": "",
                "link": ""
            },
            {
                "name": "خط أحمر",
                "time": "09:30 AM - 10:20 AM",
                "type": "مسلسل (2022)",
                "link": "https://elcinema.com/work/2075173/"
            },
            {
                "name": "برنامج - خير يبقى",
                "time": "10:20 AM - 10:30 AM",
                "type": "",
                "link": ""
            }
        ]
    },
    {
        "channel_name": "ديسكفري",
        "channel_logo": "https://media0101.elcinema.com/tvguide/1272_2.png",
        "programs": [
            {
                "name": "Salvage Hunters  -  Episode 16",
                "time": "07:24 AM - 08:10 AM",
                "type": "",
                "link": ""
            },
            {
                "name": "Gold Rush  -  Gold, Guns, And Bears",
                "time": "08:10 AM - 09:00 AM",
                "type": "",
                "link": ""
            },
            {
                "name": "Gold Rush  -  Running Dirt",
                "time": "09:00 AM - 09:50 AM",
                "type": "",
                "link": ""
            },
            {
                "name": "Gold Rush  -  The Ultimate Price",
                "time": "09:50 AM - 10:40 AM",
                "type": "",
                "link": ""
            }
        ]
    },
    {
        "channel_name": "ذكريات",
        "channel_logo": "https://media0101.elcinema.com/tvguide/1366_2.png",
        "programs": [
            {
                "name": "الليل وآخره",
                "time": "07:30 AM - 08:30 AM",
                "type": "مسلسل (2003)",
                "link": "https://elcinema.com/work/1011218/"
            },
            {
                "name": "شمس الأغوار",
                "time": "08:30 AM - 09:30 AM",
                "type": "مسلسل (1981)",
                "link": "https://elcinema.com/work/1579423/"
            },
            {
                "name": "برنامج تيلي ماتش",
                "time": "09:30 AM - 10:30 AM",
                "type": "",
                "link": ""
            }
        ]
    },
    {
        "channel_name": "ميكس وان",
        "channel_logo": "https://media0101.elcinema.com/tvguide/1373_2.png",
        "programs": [
            {
                "name": "Love and Secrets",
                "time": "08:00 AM - 09:00 AM",
                "type": "مسلسل (2019)",
                "link": "https://elcinema.com/work/2099314/"
            },
            {
                "name": "عروس إسطنبول",
                "time": "09:00 AM - 10:00 AM",
                "type": "مسلسل (2017)",
                "link": "https://elcinema.com/work/2053294/"
            },
            {
                "name": "برنامج في رحاب الكتاب والسنة",
                "time": "10:00 AM - 11:00 AM",
                "type": "",
                "link": ""
            }
        ]
    },
    {
        "channel_name": "النهار",
        "channel_logo": "https://media0101.elcinema.com/tvguide/1193_2.png",
        "programs": [
            {
                "name": "إسأل مع دعاء",
                "time": "08:00 AM - 08:30 AM",
                "type": "ﺑﺮﻧﺎﻣﺞ (2018)",
                "link": "https://elcinema.com/work/2051634/"
            },
            {
                "name": "برنامج بينا كلام",
                "time": "08:30 AM - 09:00 AM",
                "type": "",
                "link": ""
            },
            {
                "name": "برنامج الستات",
                "time": "09:00 AM - 11:00 AM",
                "type": "",
                "link": ""
            }
        ]
    },
    {
        "channel_name": "السومرية",
        "channel_logo": "https://media0101.elcinema.com/tvguide/1301_2.png",
        "programs": [
            {
                "name": "نشرة اخبار السومرية",
                "time": "07:45 AM - 09:00 AM",
                "type": "",
                "link": ""
            },
            {
                "name": "برنامج يوروماكس",
                "time": "09:00 AM - 09:30 AM",
                "type": "",
                "link": ""
            },
            {
                "name": "موضي قطعة من ذهب",
                "time": "09:30 AM - 11:00 AM",
                "type": "مسلسل (2019)",
                "link": "https://elcinema.com/work/2051975/"
            }
        ]
    },
    {
        "channel_name": "دبي",
        "channel_logo": "https://media0101.elcinema.com/tvguide/1169_2.png",
        "programs": [
            {
                "name": "Mehmed: Fetihler Sultani S2",
                "time": "08:00 AM - 09:00 AM",
                "type": "مسلسل (2024)",
                "link": "https://elcinema.com/work/2098117/"
            },
            {
                "name": "La promesa",
                "time": "09:00 AM - 10:00 AM",
                "type": "مسلسل (2022)",
                "link": "https://elcinema.com/work/2085536/"
            },
            {
                "name": "ساعته وتاريخه ج2",
                "time": "10:00 AM - 11:00 AM",
                "type": "مسلسل (2025)",
                "link": "https://elcinema.com/work/2091983/"
            }
        ]
    },
    {
        "channel_name": "القاهرة والناس 2",
        "channel_logo": "https://media0101.elcinema.com/tvguide/1252_2.png",
        "programs": [
            {
                "name": "فيلم عربي",
                "time": "07:00 AM - 09:00 AM",
                "type": "",
                "link": ""
            },
            {
                "name": "برنامج مي شو",
                "time": "09:00 AM - 10:00 AM",
                "type": "",
                "link": ""
            },
            {
                "name": "بيت الشدة",
                "time": "10:00 AM - 11:00 AM",
                "type": "مسلسل (2022)",
                "link": "https://elcinema.com/work/2073124/"
            }
        ]
    },
    {
        "channel_name": "المغربية الثانية",
        "channel_logo": "https://media0101.elcinema.com/tvguide/1353_2.png",
        "programs": [
            {
                "name": "أخبار الظهيرة",
                "time": "07:45 AM - 08:40 AM",
                "type": "",
                "link": ""
            },
            {
                "name": "برنامج ألحان عشقناها",
                "time": "08:40 AM - 09:50 AM",
                "type": "",
                "link": ""
            },
            {
                "name": "النشرة الأمازيغية",
                "time": "09:50 AM - 10:00 AM",
                "type": "",
                "link": ""
            },
            {
                "name": "لمكتوب",
                "time": "10:00 AM - 11:00 AM",
                "type": "مسلسل (2022)",
                "link": "https://elcinema.com/work/2073136/"
            }
        ]
    },
    {
        "channel_name": "بي إن موفيز بريمير",
        "channel_logo": "https://media0101.elcinema.com/tvguide/1322_2.png",
        "programs": [
            {
                "name": "Karate Kid: Legends",
                "time": "07:15 AM - 08:45 AM",
                "type": "فيلم (2025)",
                "link": "https://elcinema.com/work/2089966/"
            },
            {
                "name": "The Lockdown",
                "time": "08:45 AM - 10:45 AM",
                "type": "فيلم (2024)",
                "link": "https://elcinema.com/work/2097626/"
            }
        ]
    },
    {
        "channel_name": "بي إن سيريس إتش دي 2",
        "channel_logo": "https://media0101.elcinema.com/tvguide/1328_2.png",
        "programs": [
            {
                "name": "The Agency: Central Intelligence",
                "time": "08:00 AM - 09:00 AM",
                "type": "مسلسل (2024)",
                "link": "https://elcinema.com/work/2092351/"
            },
            {
                "name": "Star Trek: Discovery S5",
                "time": "09:00 AM - 10:00 AM",
                "type": "مسلسل (2024)",
                "link": "https://elcinema.com/work/2092869/"
            },
            {
                "name": "Star Trek: Strange New Worlds S3",
                "time": "10:00 AM - 11:00 AM",
                "type": "مسلسل (2025)",
                "link": "https://elcinema.com/work/2097875/"
            }
        ]
    },
    {
        "channel_name": "روتانا سينما",
        "channel_logo": "https://media0101.elcinema.com/tvguide/1289_2.png",
        "programs": [
            {
                "name": "خيال مآتة",
                "time": "07:00 AM - 09:00 AM",
                "type": "فيلم (2019)",
                "link": "https://elcinema.com/work/2056773/"
            },
            {
                "name": "لف ودوران",
                "time": "09:00 AM - 11:00 AM",
                "type": "فيلم (2016)",
                "link": "https://elcinema.com/work/2044411/"
            }
        ]
    },
    {
        "channel_name": "إم بي سي 4",
        "channel_logo": "https://media0101.elcinema.com/tvguide/1129_2.png",
        "programs": [
            {
                "name": "القدر",
                "time": "06:50 AM - 11:00 AM",
                "type": "مسلسل (2024)",
                "link": "https://elcinema.com/work/2091122/"
            }
        ]
    },
    {
        "channel_name": "يو تي في",
        "channel_logo": "https://media0101.elcinema.com/tvguide/1367_2.png",
        "programs": [
            {
                "name": "برنامج",
                "time": "08:00 AM - 09:00 AM",
                "type": "",
                "link": ""
            },
            {
                "name": "برنامج",
                "time": "09:00 AM - 10:00 AM",
                "type": "",
                "link": ""
            },
            {
                "name": "برنامج مساؤكم",
                "time": "10:00 AM - 11:00 AM",
                "type": "",
                "link": ""
            }
        ]
    },
    {
        "channel_name": "ال تي في",
        "channel_logo": "https://media0101.elcinema.com/tvguide/1313_2.png",
        "programs": [
            {
                "name": "حديث المرايا (مرايا 2002)",
                "time": "08:00 AM - 09:00 AM",
                "type": "مسلسل (2002)",
                "link": "https://elcinema.com/work/1469045/"
            },
            {
                "name": "عائد إلى حيفا",
                "time": "09:00 AM - 10:00 AM",
                "type": "مسلسل (2004)",
                "link": "https://elcinema.com/work/1011038/"
            },
            {
                "name": "رفيف وعكرمة",
                "time": "10:00 AM - 11:00 AM",
                "type": "مسلسل (2008)",
                "link": "https://elcinema.com/work/1777508/"
            }
        ]
    },
    {
        "channel_name": "المصرية",
        "channel_logo": "https://media0101.elcinema.com/tvguide/1119_2.png",
        "programs": [
            {
                "name": "لهفة",
                "time": "08:00 AM - 08:40 AM",
                "type": "مسلسل (2015)",
                "link": "https://elcinema.com/work/2017262/"
            },
            {
                "name": "المغامرون الخمسة",
                "time": "08:40 AM - 09:00 AM",
                "type": "مسلسل (2002)",
                "link": "https://elcinema.com/work/2039218/"
            },
            {
                "name": "نشرة الثالثة",
                "time": "09:00 AM - 10:00 AM",
                "type": "",
                "link": ""
            },
            {
                "name": "برنامج",
                "time": "10:00 AM - 11:00 AM",
                "type": "",
                "link": ""
            }
        ]
    },
    {
        "channel_name": "روتانا أفلام بلاس",
        "channel_logo": "https://media0101.elcinema.com/tvguide/1218_2.png",
        "programs": [
            {
                "name": "أحمد نوتردام",
                "time": "07:00 AM - 08:30 AM",
                "type": "فيلم (2021)",
                "link": "https://elcinema.com/work/2061752/"
            },
            {
                "name": "محمد حسين",
                "time": "08:30 AM - 10:00 AM",
                "type": "فيلم (2019)",
                "link": "https://elcinema.com/work/2052720/"
            },
            {
                "name": "كريستال",
                "time": "10:00 AM - 11:30 AM",
                "type": "فيلم (1993)",
                "link": "https://elcinema.com/work/1006718/"
            }
        ]
    },
    {
        "channel_name": "إم بي سي دراما",
        "channel_logo": "https://media0101.elcinema.com/tvguide/1194_2.png",
        "programs": [
            {
                "name": "ملوك الجدعنة",
                "time": "07:55 AM - 08:55 AM",
                "type": "مسلسل (2021)",
                "link": "https://elcinema.com/work/2066146/"
            },
            {
                "name": "ستيلتو",
                "time": "08:55 AM - 09:55 AM",
                "type": "مسلسل (2022)",
                "link": "https://elcinema.com/work/2071513/"
            },
            {
                "name": "Wild Bees",
                "time": "09:55 AM - 11:00 AM",
                "type": "مسلسل (2019)",
                "link": "https://elcinema.com/work/2085365/"
            }
        ]
    },
    {
        "channel_name": "أو إس إن كيدز",
        "channel_logo": "https://media0101.elcinema.com/tvguide/1232_2.png",
        "programs": [
            {
                "name": "Tee and Mo",
                "time": "07:58 AM - 08:05 AM",
                "type": "مسلسل - ﺭﺳﻮﻡ ﻣﺘﺤﺮﻛﺔ (2018)",
                "link": "https://elcinema.com/work/2097331/"
            },
            {
                "name": "Tee and Mo",
                "time": "08:05 AM - 08:12 AM",
                "type": "مسلسل - ﺭﺳﻮﻡ ﻣﺘﺤﺮﻛﺔ (2018)",
                "link": "https://elcinema.com/work/2097331/"
            },
            {
                "name": "Tee and Mo",
                "time": "08:12 AM - 08:19 AM",
                "type": "مسلسل - ﺭﺳﻮﻡ ﻣﺘﺤﺮﻛﺔ (2018)",
                "link": "https://elcinema.com/work/2097331/"
            },
            {
                "name": "Tee and Mo",
                "time": "08:19 AM - 08:26 AM",
                "type": "مسلسل - ﺭﺳﻮﻡ ﻣﺘﺤﺮﻛﺔ (2018)",
                "link": "https://elcinema.com/work/2097331/"
            },
            {
                "name": "Tee and Mo",
                "time": "08:26 AM - 08:33 AM",
                "type": "مسلسل - ﺭﺳﻮﻡ ﻣﺘﺤﺮﻛﺔ (2018)",
                "link": "https://elcinema.com/work/2097331/"
            },
            {
                "name": "Tee and Mo",
                "time": "08:33 AM - 08:40 AM",
                "type": "مسلسل - ﺭﺳﻮﻡ ﻣﺘﺤﺮﻛﺔ (2018)",
                "link": "https://elcinema.com/work/2097331/"
            },
            {
                "name": "Tee and Mo",
                "time": "08:40 AM - 08:47 AM",
                "type": "مسلسل - ﺭﺳﻮﻡ ﻣﺘﺤﺮﻛﺔ (2018)",
                "link": "https://elcinema.com/work/2097331/"
            },
            {
                "name": "Tee and Mo",
                "time": "08:47 AM - 08:54 AM",
                "type": "مسلسل - ﺭﺳﻮﻡ ﻣﺘﺤﺮﻛﺔ (2018)",
                "link": "https://elcinema.com/work/2097331/"
            },
            {
                "name": "Tee and Mo",
                "time": "08:54 AM - 09:00 AM",
                "type": "مسلسل - ﺭﺳﻮﻡ ﻣﺘﺤﺮﻛﺔ (2018)",
                "link": "https://elcinema.com/work/2097331/"
            },
            {
                "name": "Enchantimals: Tales from Everwilde",
                "time": "09:00 AM - 09:12 AM",
                "type": "مسلسل - ﺭﺳﻮﻡ ﻣﺘﺤﺮﻛﺔ (2018)",
                "link": "https://elcinema.com/work/2097465/"
            },
            {
                "name": "Enchantimals: Tales from Everwilde",
                "time": "09:12 AM - 09:24 AM",
                "type": "مسلسل - ﺭﺳﻮﻡ ﻣﺘﺤﺮﻛﺔ (2018)",
                "link": "https://elcinema.com/work/2097465/"
            },
            {
                "name": "Enchantimals: Tales from Everwilde",
                "time": "09:24 AM - 09:36 AM",
                "type": "مسلسل - ﺭﺳﻮﻡ ﻣﺘﺤﺮﻛﺔ (2018)",
                "link": "https://elcinema.com/work/2097465/"
            },
            {
                "name": "Enchantimals: Tales from Everwilde S2",
                "time": "09:36 AM - 09:41 AM",
                "type": "مسلسل (2019)",
                "link": "https://elcinema.com/work/2097668/"
            },
            {
                "name": "Enchantimals: Tales from Everwilde S2",
                "time": "09:41 AM - 09:46 AM",
                "type": "مسلسل (2019)",
                "link": "https://elcinema.com/work/2097668/"
            },
            {
                "name": "Ronja, the Robber's Daughter",
                "time": "09:46 AM - 10:11 AM",
                "type": "مسلسل - ﺭﺳﻮﻡ ﻣﺘﺤﺮﻛﺔ (2014)",
                "link": "https://elcinema.com/work/2096287/"
            },
            {
                "name": "Ronja, the Robber's Daughter",
                "time": "10:11 AM - 10:36 AM",
                "type": "مسلسل - ﺭﺳﻮﻡ ﻣﺘﺤﺮﻛﺔ (2014)",
                "link": "https://elcinema.com/work/2096287/"
            }
        ]
    },
    {
        "channel_name": "إم بي سي مصر",
        "channel_logo": "https://media0101.elcinema.com/tvguide/1239_2.png",
        "programs": [
            {
                "name": "العتاولة 2",
                "time": "08:00 AM - 11:30 AM",
                "type": "مسلسل (2025)",
                "link": "https://elcinema.com/work/2089649/"
            }
        ]
    },
    {
        "channel_name": "الأولى المغربية",
        "channel_logo": "https://media0101.elcinema.com/tvguide/1312_2.png",
        "programs": [
            {
                "name": "ﺍﻷﺧﺒﺎﺭ . ﺃﺧﺒﺎﺭ ﺍﻟﻈﻬﻴﺮﺓ",
                "time": "08:00 AM - 08:20 AM",
                "type": "",
                "link": ""
            },
            {
                "name": "عام ونهار",
                "time": "08:20 AM - 09:00 AM",
                "type": "مسلسل (2024)",
                "link": "https://elcinema.com/work/2086528/"
            },
            {
                "name": "ﺍﻷﺧﺒﺎﺭ . ﺍﻷﺧﺒﺎﺭ ﺍﻷﻣﺎﺯﻳﻐﻴﺔ",
                "time": "09:00 AM - 09:20 AM",
                "type": "",
                "link": ""
            },
            {
                "name": "ﺍﻷﺧﺒﺎﺭ . ﺍﻷﺧﺒﺎﺭ ﺍﻹﺳﺒﺎﻧﻴﺔ",
                "time": "09:20 AM - 09:40 AM",
                "type": "",
                "link": ""
            },
            {
                "name": "برنامج نقطة الي السطر",
                "time": "09:40 AM - 10:40 AM",
                "type": "",
                "link": ""
            }
        ]
    },
    {
        "channel_name": "دبي وان",
        "channel_logo": "https://media0101.elcinema.com/tvguide/1173_2.png",
        "programs": [
            {
                "name": "Underwater",
                "time": "08:00 AM - 10:00 AM",
                "type": "فيلم (2020)",
                "link": "https://elcinema.com/work/2050064/"
            },
            {
                "name": "Ice Age: Dawn of the Dinosaurs",
                "time": "10:00 AM - 12:00 PM",
                "type": "فيلم (2009)",
                "link": "https://elcinema.com/work/1999291/"
            }
        ]
    },
    {
        "channel_name": "زي ألوان",
        "channel_logo": "https://media0101.elcinema.com/tvguide/1261_2.png",
        "programs": [
            {
                "name": "مسلسل",
                "time": "08:00 AM - 09:00 AM",
                "type": "",
                "link": ""
            },
            {
                "name": "سهرانين",
                "time": "09:00 AM - 10:00 AM",
                "type": "ﺑﺮﻧﺎﻣﺞ (2019)",
                "link": "https://elcinema.com/work/2054409/"
            },
            {
                "name": "Chrysalis S3",
                "time": "10:00 AM - 11:00 AM",
                "type": "مسلسل (2022)",
                "link": "https://elcinema.com/work/2085663/"
            }
        ]
    },
    {
        "channel_name": "الأردن",
        "channel_logo": "https://media0101.elcinema.com/tvguide/1314_2.png",
        "programs": [
            {
                "name": "برنامج شوق و حنين",
                "time": "08:00 AM - 08:30 AM",
                "type": "",
                "link": ""
            },
            {
                "name": "الرسوم ىالمتحركة",
                "time": "08:30 AM - 09:00 AM",
                "type": "",
                "link": ""
            },
            {
                "name": "برنامج افرح و امرح",
                "time": "09:00 AM - 10:00 AM",
                "type": "",
                "link": ""
            },
            {
                "name": "برنامج بيتك",
                "time": "10:00 AM - 10:45 AM",
                "type": "",
                "link": ""
            }
        ]
    },
    {
        "channel_name": "روتانا خليجية",
        "channel_logo": "https://media0101.elcinema.com/tvguide/1149_2.png",
        "programs": [
            {
                "name": "بحبك",
                "time": "08:00 AM - 10:00 AM",
                "type": "فيلم (2022)",
                "link": "https://elcinema.com/work/2074339/"
            },
            {
                "name": "سيدتي",
                "time": "10:00 AM - 12:00 PM",
                "type": "ﺑﺮﻧﺎﻣﺞ (2008)",
                "link": "https://elcinema.com/work/2041433/"
            }
        ]
    },
    {
        "channel_name": "روتانا سينما مصر",
        "channel_logo": "https://media0101.elcinema.com/tvguide/1148_2.png",
        "programs": [
            {
                "name": "الكنز: الحقيقة والخيال",
                "time": "07:00 AM - 09:00 AM",
                "type": "فيلم (2017)",
                "link": "https://elcinema.com/work/2043112/"
            },
            {
                "name": "أبناء وقتلة",
                "time": "09:00 AM - 11:00 AM",
                "type": "فيلم (1987)",
                "link": "https://elcinema.com/work/1008469/"
            }
        ]
    },
    {
        "channel_name": "إم بي سي مصر 2",
        "channel_logo": "https://media0101.elcinema.com/tvguide/1278_2.png",
        "programs": [
            {
                "name": "Aashiqana",
                "time": "06:00 AM - 08:15 AM",
                "type": "مسلسل (2022)",
                "link": "https://elcinema.com/work/2093146/"
            },
            {
                "name": "راجل وست ستات ج7",
                "time": "08:15 AM - 08:45 AM",
                "type": "مسلسل (2010)",
                "link": "https://elcinema.com/work/1706885/"
            },
            {
                "name": "برنامج الكورة مع فايق",
                "time": "08:45 AM - 10:20 AM",
                "type": "",
                "link": ""
            },
            {
                "name": "عائلة الحاج نعمان ج1",
                "time": "10:20 AM - 12:27 PM",
                "type": "مسلسل (2017)",
                "link": "https://elcinema.com/work/2047460/"
            }
        ]
    },
    {
        "channel_name": "ماسة",
        "channel_logo": "https://media0101.elcinema.com/tvguide/1401_2.png",
        "programs": [
            {
                "name": "برنامج",
                "time": "07:00 AM - 08:15 AM",
                "type": "",
                "link": ""
            },
            {
                "name": "برنامج",
                "time": "08:15 AM - 09:40 AM",
                "type": "",
                "link": ""
            },
            {
                "name": "برنامج ريف الحبايب",
                "time": "09:40 AM - 10:10 AM",
                "type": "",
                "link": ""
            },
            {
                "name": "برنامج صحبة",
                "time": "10:10 AM - 10:50 AM",
                "type": "",
                "link": ""
            }
        ]
    },
    {
        "channel_name": "أو إس إن موفيز هوليوود",
        "channel_logo": "https://media0101.elcinema.com/tvguide/1391_2.png",
        "programs": [
            {
                "name": "Gravity",
                "time": "07:50 AM - 09:20 AM",
                "type": "فيلم (2013)",
                "link": "https://elcinema.com/work/2006332/"
            },
            {
                "name": "Eternal Sunshine of the Spotless Mind",
                "time": "09:20 AM - 11:05 AM",
                "type": "فيلم (2004)",
                "link": "https://elcinema.com/work/2001190/"
            }
        ]
    },
    {
        "channel_name": "الوسط",
        "channel_logo": "https://media0101.elcinema.com/tvguide/1383_2.png",
        "programs": [
            {
                "name": "برنامج",
                "time": "08:00 AM - 09:00 AM",
                "type": "",
                "link": ""
            },
            {
                "name": "برنامج",
                "time": "09:00 AM - 10:00 AM",
                "type": "",
                "link": ""
            },
            {
                "name": "برنامج",
                "time": "10:00 AM - 11:00 AM",
                "type": "",
                "link": ""
            }
        ]
    },
    {
        "channel_name": "سي بي سي دراما",
        "channel_logo": "https://media0101.elcinema.com/tvguide/1199_2.png",
        "programs": [
            {
                "name": "درش",
                "time": "08:00 AM - 09:00 AM",
                "type": "مسلسل (2026)",
                "link": "https://elcinema.com/work/2096819/"
            },
            {
                "name": "راس الغول",
                "time": "09:00 AM - 10:00 AM",
                "type": "مسلسل (2016)",
                "link": "https://elcinema.com/work/2033147/"
            },
            {
                "name": "العيلة دي",
                "time": "10:00 AM - 11:00 AM",
                "type": "مسلسل (2022)",
                "link": "https://elcinema.com/work/2076576/"
            }
        ]
    },
    {
        "channel_name": "سما دبي",
        "channel_logo": "https://media0101.elcinema.com/tvguide/1177_2.png",
        "programs": [
            {
                "name": "برنامج ولفة",
                "time": "08:00 AM - 09:00 AM",
                "type": "",
                "link": ""
            },
            {
                "name": "برنامج ذاكرة الاعلام",
                "time": "09:00 AM - 10:00 AM",
                "type": "",
                "link": ""
            },
            {
                "name": "برنامج بصمات",
                "time": "10:00 AM - 10:30 AM",
                "type": "",
                "link": ""
            }
        ]
    },
    {
        "channel_name": "أو إس إن موفيز بريميير",
        "channel_logo": "https://media0101.elcinema.com/tvguide/1213_2.png",
        "programs": [
            {
                "name": "John Wick: Chapter 4",
                "time": "05:45 AM - 08:35 AM",
                "type": "فيلم (2023)",
                "link": "https://elcinema.com/work/2075227/"
            },
            {
                "name": "Day of Reckoning",
                "time": "08:35 AM - 10:25 AM",
                "type": "فيلم (2025)",
                "link": "https://elcinema.com/work/2092705/"
            },
            {
                "name": "Beyond the Likes",
                "time": "10:25 AM - 12:20 PM",
                "type": "فيلم (2024)",
                "link": "https://elcinema.com/work/2090387/"
            }
        ]
    },
    {
        "channel_name": "أون دراما",
        "channel_logo": "https://media0101.elcinema.com/tvguide/1134_2.png",
        "programs": [
            {
                "name": "إلا أنا",
                "time": "08:00 AM - 08:40 AM",
                "type": "مسلسل (2020)",
                "link": "https://elcinema.com/work/2061816/"
            },
            {
                "name": "العودة",
                "time": "08:40 AM - 10:00 AM",
                "type": "مسلسل (2023)",
                "link": "https://elcinema.com/work/2083073/"
            },
            {
                "name": "مناعة",
                "time": "10:00 AM - 11:00 AM",
                "type": "مسلسل (2026)",
                "link": "https://elcinema.com/work/2097616/"
            }
        ]
    },
    {
        "channel_name": "الحياة",
        "channel_logo": "https://media0101.elcinema.com/tvguide/1137_2.png",
        "programs": [
            {
                "name": "برنامج دولة التلاوة",
                "time": "07:00 AM - 09:00 AM",
                "type": "",
                "link": ""
            },
            {
                "name": "برنامج الدنيا بخير",
                "time": "09:00 AM - 09:45 AM",
                "type": "",
                "link": ""
            },
            {
                "name": "الإمام الطيب",
                "time": "09:45 AM - 10:00 AM",
                "type": "ﺑﺮﻧﺎﻣﺞ (2016)",
                "link": "https://elcinema.com/work/2043888/"
            },
            {
                "name": "شارع شريف ج4",
                "time": "10:00 AM - 12:00 PM",
                "type": "ﺑﺮﻧﺎﻣﺞ (2018)",
                "link": "https://elcinema.com/work/2051640/"
            }
        ]
    },
    {
        "channel_name": "بي إن موفيز أكشن",
        "channel_logo": "https://media0101.elcinema.com/tvguide/1323_2.png",
        "programs": [
            {
                "name": "Star Trek",
                "time": "06:45 AM - 09:00 AM",
                "type": "فيلم (2009)",
                "link": "https://elcinema.com/work/1999283/"
            },
            {
                "name": "Star Trek Into Darkness",
                "time": "09:00 AM - 11:15 AM",
                "type": "فيلم (2013)",
                "link": "https://elcinema.com/work/2019204/"
            }
        ]
    },
    {
        "channel_name": "روتانا كوميدي",
        "channel_logo": "https://media0101.elcinema.com/tvguide/1358_2.png",
        "programs": [
            {
                "name": "قلب أمه",
                "time": "07:00 AM - 09:00 AM",
                "type": "فيلم (2018)",
                "link": "https://elcinema.com/work/2051036/"
            },
            {
                "name": "الستات مايعرفوش يكدبوا",
                "time": "09:00 AM - 11:00 AM",
                "type": "فيلم (1954)",
                "link": "https://elcinema.com/work/1010317/"
            }
        ]
    },
    {
        "channel_name": "تلفزيون حضرموت",
        "channel_logo": "https://media0101.elcinema.com/tvguide/1374_2.png",
        "programs": [
            {
                "name": "برنامج",
                "time": "08:00 AM - 09:00 AM",
                "type": "",
                "link": ""
            },
            {
                "name": "برنامج",
                "time": "09:00 AM - 10:00 AM",
                "type": "",
                "link": ""
            },
            {
                "name": "برنامج",
                "time": "10:00 AM - 11:00 AM",
                "type": "",
                "link": ""
            }
        ]
    },
    {
        "channel_name": "الظفرة",
        "channel_logo": "https://media0101.elcinema.com/tvguide/1264_2.png",
        "programs": [
            {
                "name": "عزيز الروح",
                "time": "08:00 AM - 09:00 AM",
                "type": "مسلسل (2023)",
                "link": "https://elcinema.com/work/2076031/"
            },
            {
                "name": "حق عرب",
                "time": "09:00 AM - 10:00 AM",
                "type": "مسلسل (2024)",
                "link": "https://elcinema.com/work/2082468/"
            },
            {
                "name": "نشميات من البادية",
                "time": "10:00 AM - 11:00 AM",
                "type": "مسلسل (2022)",
                "link": "https://elcinema.com/work/2073605/"
            }
        ]
    },
    {
        "channel_name": "بي إن دراما",
        "channel_logo": "https://media0101.elcinema.com/tvguide/1309_2.png",
        "programs": [
            {
                "name": "أفكار أمي",
                "time": "08:00 AM - 09:00 AM",
                "type": "مسلسل (2025)",
                "link": "https://elcinema.com/work/2088176/"
            },
            {
                "name": "أفكار أمي",
                "time": "09:00 AM - 10:00 AM",
                "type": "مسلسل (2025)",
                "link": "https://elcinema.com/work/2088176/"
            },
            {
                "name": "أفكار أمي",
                "time": "10:00 AM - 11:00 AM",
                "type": "مسلسل (2025)",
                "link": "https://elcinema.com/work/2088176/"
            }
        ]
    },
    {
        "channel_name": "الجديد",
        "channel_logo": "https://media0101.elcinema.com/tvguide/1216_2.png",
        "programs": [
            {
                "name": "Last Summer",
                "time": "07:30 AM - 08:30 AM",
                "type": "مسلسل (2021)",
                "link": "https://elcinema.com/work/2085173/"
            },
            {
                "name": "نشرة الأخبار",
                "time": "08:30 AM - 09:00 AM",
                "type": "",
                "link": ""
            },
            {
                "name": "برنامج هنا بيروت",
                "time": "09:00 AM - 10:00 AM",
                "type": "",
                "link": ""
            },
            {
                "name": "برنامج وهلق شو",
                "time": "10:00 AM - 11:30 AM",
                "type": "",
                "link": ""
            }
        ]
    },
    {
        "channel_name": "صدى البلد 2",
        "channel_logo": "https://media0101.elcinema.com/tvguide/1279_2.png",
        "programs": [
            {
                "name": "برنامج ملعب البلد",
                "time": "08:00 AM - 09:00 AM",
                "type": "",
                "link": ""
            },
            {
                "name": "برنامج الماتش",
                "time": "09:00 AM - 10:00 AM",
                "type": "",
                "link": ""
            },
            {
                "name": "برنامج صحتك وبس",
                "time": "10:00 AM - 11:00 AM",
                "type": "",
                "link": ""
            }
        ]
    },
    {
        "channel_name": "بي إن موفيز دراما",
        "channel_logo": "https://media0101.elcinema.com/tvguide/1324_2.png",
        "programs": [
            {
                "name": "The Longest Yard",
                "time": "07:00 AM - 09:00 AM",
                "type": "فيلم (2005)",
                "link": "https://elcinema.com/work/2000975/"
            },
            {
                "name": "Cinderella's Curse",
                "time": "09:00 AM - 10:30 AM",
                "type": "فيلم (2024)",
                "link": "https://elcinema.com/work/2086543/"
            }
        ]
    },
    {
        "channel_name": "بي إن موفيز فاميلي",
        "channel_logo": "https://media0101.elcinema.com/tvguide/1325_2.png",
        "programs": [
            {
                "name": "The Adventures of Sharkboy and Lavagirl 3-D",
                "time": "07:00 AM - 08:30 AM",
                "type": "فيلم (2005)",
                "link": "https://elcinema.com/work/2008995/"
            },
            {
                "name": "Paddington in Peru",
                "time": "08:30 AM - 10:15 AM",
                "type": "فيلم (2024)",
                "link": "https://elcinema.com/work/2083864/"
            },
            {
                "name": "Harold and the Purple Crayon",
                "time": "10:15 AM - 11:45 AM",
                "type": "فيلم (2024)",
                "link": "https://elcinema.com/work/2075261/"
            }
        ]
    },
    {
        "channel_name": "ستار موفيز",
        "channel_logo": "https://media0101.elcinema.com/tvguide/1212_2.png",
        "programs": [
            {
                "name": "How to Deter a Robber",
                "time": "07:40 AM - 09:05 AM",
                "type": "فيلم (2020)",
                "link": "https://elcinema.com/work/2098379/"
            },
            {
                "name": "King of Thieves",
                "time": "09:05 AM - 11:05 AM",
                "type": "فيلم (2018)",
                "link": "https://elcinema.com/work/2052419/"
            }
        ]
    },
    {
        "channel_name": "روتانا كيدز",
        "channel_logo": "https://media0101.elcinema.com/tvguide/1356_2.png",
        "programs": [
            {
                "name": "Nutri Ventures",
                "time": "08:00 AM - 08:10 AM",
                "type": "مسلسل (2013)",
                "link": "https://elcinema.com/work/2063569/"
            },
            {
                "name": "Eena, Meena, Deeka",
                "time": "08:10 AM - 08:20 AM",
                "type": "مسلسل (2015)",
                "link": "https://elcinema.com/work/2063561/"
            },
            {
                "name": "Eena, Meena, Deeka",
                "time": "08:20 AM - 08:45 AM",
                "type": "مسلسل (2015)",
                "link": "https://elcinema.com/work/2063561/"
            },
            {
                "name": "Vroomiz S2",
                "time": "08:45 AM - 09:00 AM",
                "type": "مسلسل - ﺭﺳﻮﻡ ﻣﺘﺤﺮﻛﺔ (2016)",
                "link": "https://elcinema.com/work/2085650/"
            },
            {
                "name": "Gon",
                "time": "09:00 AM - 09:25 AM",
                "type": "مسلسل - ﺭﺳﻮﻡ ﻣﺘﺤﺮﻛﺔ (2012)",
                "link": "https://elcinema.com/work/2064804/"
            },
            {
                "name": "Boom & Reds",
                "time": "09:25 AM - 09:30 AM",
                "type": "مسلسل - ﺭﺳﻮﻡ ﻣﺘﺤﺮﻛﺔ (2006)",
                "link": "https://elcinema.com/work/2085648/"
            },
            {
                "name": "Shinderera monogatari",
                "time": "09:30 AM - 10:00 AM",
                "type": "مسلسل (1996)",
                "link": "https://elcinema.com/work/2075634/"
            },
            {
                "name": "Farhat: The Prince of the Desert",
                "time": "10:00 AM - 10:30 AM",
                "type": "مسلسل - ﺭﺳﻮﻡ ﻣﺘﺤﺮﻛﺔ (2004)",
                "link": "https://elcinema.com/work/2065086/"
            }
        ]
    },
    {
        "channel_name": "إم بي سي مصر دراما",
        "channel_logo": "https://media0101.elcinema.com/tvguide/1399_2.png",
        "programs": [
            {
                "name": "الفرح فرحنا",
                "time": "07:30 AM - 08:45 AM",
                "type": "مسلسل (2022)",
                "link": "https://elcinema.com/work/2072480/"
            },
            {
                "name": "زلزال",
                "time": "08:45 AM - 09:50 AM",
                "type": "مسلسل (2019)",
                "link": "https://elcinema.com/work/2006065/"
            },
            {
                "name": "ذهاب وعودة",
                "time": "09:50 AM - 10:35 AM",
                "type": "مسلسل (2015)",
                "link": "https://elcinema.com/work/2033694/"
            }
        ]
    },
    {
        "channel_name": "أو إس إن شو كايس",
        "channel_logo": "https://media0101.elcinema.com/tvguide/1394_2.png",
        "programs": [
            {
                "name": "In Treatment S3",
                "time": "07:45 AM - 08:10 AM",
                "type": "مسلسل (2010)",
                "link": "https://elcinema.com/work/2069249/"
            },
            {
                "name": "Last Week Tonight with John Oliver S6",
                "time": "08:10 AM - 09:00 AM",
                "type": "ﺑﺮﻧﺎﻣﺞ (2019)",
                "link": "https://elcinema.com/work/2094287/"
            },
            {
                "name": "Veep S7",
                "time": "09:00 AM - 09:30 AM",
                "type": "مسلسل (2019)",
                "link": "https://elcinema.com/work/2058013/"
            },
            {
                "name": "Veep S7",
                "time": "09:30 AM - 10:00 AM",
                "type": "مسلسل (2019)",
                "link": "https://elcinema.com/work/2058013/"
            },
            {
                "name": "Veep S7",
                "time": "10:00 AM - 10:30 AM",
                "type": "مسلسل (2019)",
                "link": "https://elcinema.com/work/2058013/"
            }
        ]
    },
    {
        "channel_name": "ال دي سي",
        "channel_logo": "https://media0101.elcinema.com/tvguide/1246_2.png",
        "programs": [
            {
                "name": "فيديو كليبات",
                "time": "08:00 AM - 08:30 AM",
                "type": "",
                "link": ""
            },
            {
                "name": "نشرة الاخبار",
                "time": "08:30 AM - 09:00 AM",
                "type": "",
                "link": ""
            },
            {
                "name": "أفلام ديينية",
                "time": "09:00 AM - 12:45 PM",
                "type": "",
                "link": ""
            }
        ]
    },
    {
        "channel_name": "إل بي سي",
        "channel_logo": "https://media0101.elcinema.com/tvguide/1341_2.png",
        "programs": [
            {
                "name": "سوق الكانتو",
                "time": "08:00 AM - 09:00 AM",
                "type": "مسلسل (2023)",
                "link": "https://elcinema.com/work/2077352/"
            },
            {
                "name": "أهل الخطايا",
                "time": "09:00 AM - 10:00 AM",
                "type": "مسلسل (2025)",
                "link": "https://elcinema.com/work/2091891/"
            },
            {
                "name": "سيدتي",
                "time": "10:00 AM - 12:00 PM",
                "type": "ﺑﺮﻧﺎﻣﺞ (2008)",
                "link": "https://elcinema.com/work/2041433/"
            }
        ]
    },
    {
        "channel_name": "وان دراما",
        "channel_logo": "https://media0101.elcinema.com/tvguide/1405_2.png",
        "programs": [
            {
                "name": "Uzak Sehir",
                "time": "08:00 AM - 08:30 AM",
                "type": "مسلسل (2024)",
                "link": "https://elcinema.com/work/2091404/"
            },
            {
                "name": "Forbidden Love",
                "time": "08:30 AM - 09:15 AM",
                "type": "مسلسل (2008)",
                "link": "https://elcinema.com/work/1997628/"
            },
            {
                "name": "The Pit S4",
                "time": "09:15 AM - 10:00 AM",
                "type": "مسلسل (2020)",
                "link": "https://elcinema.com/work/2067766/"
            },
            {
                "name": "Endless Love",
                "time": "10:00 AM - 11:00 AM",
                "type": "مسلسل (2015)",
                "link": "https://elcinema.com/work/2041786/"
            }
        ]
    },
    {
        "channel_name": "أو إس إن موفيز كوميدي",
        "channel_logo": "https://media0101.elcinema.com/tvguide/1231_2.png",
        "programs": [
            {
                "name": "Rush Hour",
                "time": "07:40 AM - 09:15 AM",
                "type": "فيلم (1998)",
                "link": "https://elcinema.com/work/2004397/"
            },
            {
                "name": "Rush Hour 2",
                "time": "09:15 AM - 10:45 AM",
                "type": "فيلم (2001)",
                "link": "https://elcinema.com/work/2006362/"
            }
        ]
    },
    {
        "channel_name": "أو إس إن فاميلي موفيز",
        "channel_logo": "https://media0101.elcinema.com/tvguide/1392_2.png",
        "programs": [
            {
                "name": "Shrek 2",
                "time": "07:12 AM - 08:42 AM",
                "type": "فيلم - ﺭﺳﻮﻡ ﻣﺘﺤﺮﻛﺔ (2004)",
                "link": "https://elcinema.com/work/2003247/"
            },
            {
                "name": "Harry Potter and the Deathly Hallows: Part 1",
                "time": "08:42 AM - 11:03 AM",
                "type": "فيلم (2010)",
                "link": "https://elcinema.com/work/1797338/"
            }
        ]
    },
    {
        "channel_name": "الشروق الجزائرية",
        "channel_logo": "https://media0101.elcinema.com/tvguide/1315_2.png",
        "programs": [
            {
                "name": "برنامج",
                "time": "07:00 AM - 08:30 AM",
                "type": "",
                "link": ""
            },
            {
                "name": "برنامج ألو شاف",
                "time": "08:30 AM - 10:15 AM",
                "type": "",
                "link": ""
            },
            {
                "name": "Veliaht",
                "time": "10:15 AM - 11:10 AM",
                "type": "مسلسل (2025)",
                "link": "https://elcinema.com/work/2096900/"
            }
        ]
    },
    {
        "channel_name": "اﻹمارات",
        "channel_logo": "https://media0101.elcinema.com/tvguide/1135_2.png",
        "programs": [
            {
                "name": "أمونة المزيونة",
                "time": "08:00 AM - 08:15 AM",
                "type": "مسلسل - ﺭﺳﻮﻡ ﻣﺘﺤﺮﻛﺔ (2015)",
                "link": "https://elcinema.com/work/2082970/"
            },
            {
                "name": "كراملة",
                "time": "08:15 AM - 08:30 AM",
                "type": "مسلسل - ﺭﺳﻮﻡ ﻣﺘﺤﺮﻛﺔ (2016)",
                "link": "https://elcinema.com/work/2095895/"
            },
            {
                "name": "برنامج غوردن رامزي: أسرار الطعام",
                "time": "08:30 AM - 09:30 AM",
                "type": "",
                "link": ""
            },
            {
                "name": "برنامج نرويها",
                "time": "09:30 AM - 10:00 AM",
                "type": "",
                "link": ""
            },
            {
                "name": "هيا الروح",
                "time": "10:00 AM - 11:00 AM",
                "type": "مسلسل (2022)",
                "link": "https://elcinema.com/work/2071315/"
            }
        ]
    },
    {
        "channel_name": "أو إس إن ياهلا",
        "channel_logo": "https://media0101.elcinema.com/tvguide/1205_2.png",
        "programs": [
            {
                "name": "درب الذهب",
                "time": "07:40 AM - 08:30 AM",
                "type": "مسلسل (2026)",
                "link": "https://elcinema.com/work/2097838/"
            },
            {
                "name": "درب الذهب",
                "time": "08:30 AM - 09:20 AM",
                "type": "مسلسل (2026)",
                "link": "https://elcinema.com/work/2097838/"
            },
            {
                "name": "درب الذهب",
                "time": "09:20 AM - 10:10 AM",
                "type": "مسلسل (2026)",
                "link": "https://elcinema.com/work/2097838/"
            },
            {
                "name": "درب الذهب",
                "time": "10:10 AM - 11:00 AM",
                "type": "مسلسل (2026)",
                "link": "https://elcinema.com/work/2097838/"
            }
        ]
    },
    {
        "channel_name": "نايل دراما",
        "channel_logo": "https://media0101.elcinema.com/tvguide/1156_2.png",
        "programs": [
            {
                "name": "طاقة القدر",
                "time": "08:00 AM - 09:00 AM",
                "type": "مسلسل (2017)",
                "link": "https://elcinema.com/work/2044695/"
            },
            {
                "name": "هذا المساء",
                "time": "09:00 AM - 10:00 AM",
                "type": "مسلسل (2017)",
                "link": "https://elcinema.com/work/2045613/"
            },
            {
                "name": "أرابيسك: أيام حسن النعماني",
                "time": "10:00 AM - 11:00 AM",
                "type": "مسلسل (1994)",
                "link": "https://elcinema.com/work/1010599/"
            }
        ]
    },
    {
        "channel_name": "سي بي سي",
        "channel_logo": "https://media0101.elcinema.com/tvguide/1198_2.png",
        "programs": [
            {
                "name": "فيلم عربي",
                "time": "07:00 AM - 09:00 AM",
                "type": "",
                "link": ""
            },
            {
                "name": "الستات ميعرفوش يكدبوا",
                "time": "09:00 AM - 11:00 AM",
                "type": "ﺑﺮﻧﺎﻣﺞ (2011)",
                "link": "https://elcinema.com/work/2006017/"
            }
        ]
    },
    {
        "channel_name": "أو إس إن كرايم",
        "channel_logo": "https://media0101.elcinema.com/tvguide/1395_2.png",
        "programs": [
            {
                "name": "Blindspot S1",
                "time": "07:35 AM - 08:20 AM",
                "type": "مسلسل (2015)",
                "link": "https://elcinema.com/work/2040932/"
            },
            {
                "name": "Blindspot S1",
                "time": "08:20 AM - 09:10 AM",
                "type": "مسلسل (2015)",
                "link": "https://elcinema.com/work/2040932/"
            },
            {
                "name": "Blindspot S1",
                "time": "09:10 AM - 09:55 AM",
                "type": "مسلسل (2015)",
                "link": "https://elcinema.com/work/2040932/"
            },
            {
                "name": "Blindspot S1",
                "time": "09:55 AM - 10:45 AM",
                "type": "مسلسل (2015)",
                "link": "https://elcinema.com/work/2040932/"
            }
        ]
    },
    {
        "channel_name": "العراقية",
        "channel_logo": "https://media0101.elcinema.com/tvguide/1349_2.png",
        "programs": [
            {
                "name": "أصحاب المقام الرفيع",
                "time": "08:00 AM - 09:00 AM",
                "type": "مسلسل (2004)",
                "link": "https://elcinema.com/work/1010994/"
            },
            {
                "name": "برنامج",
                "time": "09:00 AM - 10:00 AM",
                "type": "",
                "link": ""
            },
            {
                "name": "برنامج",
                "time": "10:00 AM - 11:00 AM",
                "type": "",
                "link": ""
            }
        ]
    },
    {
        "channel_name": "القاهرة والناس",
        "channel_logo": "https://media0101.elcinema.com/tvguide/1174_2.png",
        "programs": [
            {
                "name": "برنامج الدكتور",
                "time": "08:00 AM - 10:00 AM",
                "type": "",
                "link": ""
            },
            {
                "name": "فيلم عربي",
                "time": "10:00 AM - 11:30 AM",
                "type": "",
                "link": ""
            }
        ]
    },
    {
        "channel_name": "إم بي سي بوليوود",
        "channel_logo": "https://media0101.elcinema.com/tvguide/1259_2.png",
        "programs": [
            {
                "name": "Seher Hone Ko Hai",
                "time": "04:50 AM - 08:25 AM",
                "type": "مسلسل (2025)",
                "link": "https://elcinema.com/work/2099382/"
            },
            {
                "name": "The Villain",
                "time": "08:25 AM - 10:30 AM",
                "type": "فيلم (2014)",
                "link": "https://elcinema.com/work/2031027/"
            }
        ]
    },
    {
        "channel_name": "نتورك بالعربية",
        "channel_logo": "https://media0101.elcinema.com/tvguide/1242_2.png",
        "programs": [
            {
                "name": "We Bare Bears S2",
                "time": "08:00 AM - 10:00 AM",
                "type": "مسلسل (2016)",
                "link": "https://elcinema.com/work/2063439/"
            },
            {
                "name": "Ben 10 S1",
                "time": "10:00 AM - 12:00 PM",
                "type": "مسلسل (2016)",
                "link": "https://elcinema.com/work/2060235/"
            }
        ]
    },
    {
        "channel_name": "رؤيا",
        "channel_logo": "https://media0101.elcinema.com/tvguide/1299_2.png",
        "programs": [
            {
                "name": "برنامج حلوة يا دنيا",
                "time": "05:30 AM - 08:30 AM",
                "type": "",
                "link": ""
            },
            {
                "name": "عشنا وشفنا (مرايا 2004)",
                "time": "08:30 AM - 09:30 AM",
                "type": "مسلسل (2004)",
                "link": "https://elcinema.com/work/1011039/"
            },
            {
                "name": "أخبار",
                "time": "09:30 AM - 10:00 AM",
                "type": "",
                "link": ""
            },
            {
                "name": "مطبخ رؤيا",
                "time": "10:00 AM - 11:30 AM",
                "type": "ﺑﺮﻧﺎﻣﺞ (2018)",
                "link": "https://elcinema.com/work/2052587/"
            }
        ]
    },
    {
        "channel_name": "أو إس إن ياهلا أفلام",
        "channel_logo": "https://media0101.elcinema.com/tvguide/1285_2.png",
        "programs": [
            {
                "name": "الهنا اللي أنا فيه",
                "time": "06:30 AM - 08:15 AM",
                "type": "فيلم (2024)",
                "link": "https://elcinema.com/work/2089034/"
            },
            {
                "name": "مستر إكس",
                "time": "08:15 AM - 10:00 AM",
                "type": "فيلم (2023)",
                "link": "https://elcinema.com/work/2073079/"
            },
            {
                "name": "بحبك",
                "time": "10:00 AM - 11:40 AM",
                "type": "فيلم (2022)",
                "link": "https://elcinema.com/work/2074339/"
            }
        ]
    },
    {
        "channel_name": "إم بي سي العراق",
        "channel_logo": "https://media0101.elcinema.com/tvguide/1340_2.png",
        "programs": [
            {
                "name": "أم أربعة وأربعين",
                "time": "05:30 AM - 09:15 AM",
                "type": "مسلسل (2025)",
                "link": "https://elcinema.com/work/2090986/"
            },
            {
                "name": "النار بالنار",
                "time": "09:15 AM - 12:00 PM",
                "type": "مسلسل (2023)",
                "link": "https://elcinema.com/work/2077224/"
            }
        ]
    },
    {
        "channel_name": "ستار أكشن",
        "channel_logo": "https://media0101.elcinema.com/tvguide/1330_2.png",
        "programs": [
            {
                "name": "The Foreigner",
                "time": "07:40 AM - 09:30 AM",
                "type": "فيلم (2017)",
                "link": "https://elcinema.com/work/2046124/"
            },
            {
                "name": "Nightsleeper",
                "time": "09:30 AM - 10:30 AM",
                "type": "مسلسل (2024)",
                "link": "https://elcinema.com/work/2096695/"
            }
        ]
    },
    {
        "channel_name": "إم بي سي ماكس",
        "channel_logo": "https://media0101.elcinema.com/tvguide/1132_2.png",
        "programs": [
            {
                "name": "Jackie",
                "time": "06:30 AM - 08:30 AM",
                "type": "فيلم (2016)",
                "link": "https://elcinema.com/work/2041768/"
            },
            {
                "name": "Catwoman",
                "time": "08:30 AM - 10:30 AM",
                "type": "فيلم (2004)",
                "link": "https://elcinema.com/work/2002273/"
            }
        ]
    },
    {
        "channel_name": "ستار ورلد",
        "channel_logo": "https://media0101.elcinema.com/tvguide/1329_2.png",
        "programs": [
            {
                "name": "Revenge S4",
                "time": "07:40 AM - 08:25 AM",
                "type": "مسلسل (2014)",
                "link": "https://elcinema.com/work/2034191/"
            },
            {
                "name": "برنامج Donal's Real Time Recipes",
                "time": "08:25 AM - 09:00 AM",
                "type": "",
                "link": ""
            },
            {
                "name": "برنامج Donal's Real Time Recipes",
                "time": "09:00 AM - 09:40 AM",
                "type": "",
                "link": ""
            },
            {
                "name": "Married at First Sight",
                "time": "09:40 AM - 11:00 AM",
                "type": "ﺑﺮﻧﺎﻣﺞ (2014)",
                "link": "https://elcinema.com/work/2052403/"
            }
        ]
    },
    {
        "channel_name": "الثانية",
        "channel_logo": "https://media0101.elcinema.com/tvguide/1398_2.png",
        "programs": [
            {
                "name": "طرب",
                "time": "07:30 AM - 08:30 AM",
                "type": "ﺑﺮﻧﺎﻣﺞ (2018)",
                "link": "https://elcinema.com/work/2075906/"
            },
            {
                "name": "برنامج",
                "time": "08:30 AM - 09:00 AM",
                "type": "",
                "link": ""
            },
            {
                "name": "برنامج",
                "time": "09:00 AM - 10:00 AM",
                "type": "",
                "link": ""
            },
            {
                "name": "كان ياما كان ج2",
                "time": "10:00 AM - 11:00 AM",
                "type": "مسلسل (1995)",
                "link": "https://elcinema.com/work/1632658/"
            }
        ]
    },
    {
        "channel_name": "أو إٍس إن ناو",
        "channel_logo": "https://media0101.elcinema.com/tvguide/1396_2.png",
        "programs": [
            {
                "name": "Gossip Girl S4",
                "time": "07:25 AM - 08:10 AM",
                "type": "مسلسل (2010)",
                "link": "https://elcinema.com/work/2012747/"
            },
            {
                "name": "Mayfair Witches S2",
                "time": "08:10 AM - 09:00 AM",
                "type": "مسلسل (2024)",
                "link": "https://elcinema.com/work/2090509/"
            },
            {
                "name": "Ultimate Rush S2",
                "time": "09:00 AM - 09:30 AM",
                "type": "ﺑﺮﻧﺎﻣﺞ (2013)",
                "link": "https://elcinema.com/work/2096159/"
            },
            {
                "name": "Dubai Hustle",
                "time": "09:30 AM - 10:00 AM",
                "type": "مسلسل (2022)",
                "link": "https://elcinema.com/work/2094525/"
            },
            {
                "name": "World's Greatest Hotels",
                "time": "10:00 AM - 10:45 AM",
                "type": "مسلسل (2019)",
                "link": "https://elcinema.com/work/2094127/"
            }
        ]
    },
    {
        "channel_name": "ماسبيرو زمان",
        "channel_logo": "https://media0101.elcinema.com/tvguide/1336_2.png",
        "programs": [
            {
                "name": "فيلم",
                "time": "07:00 AM - 09:00 AM",
                "type": "",
                "link": ""
            },
            {
                "name": "نصف ربيع الآخر",
                "time": "09:00 AM - 10:00 AM",
                "type": "مسلسل (1996)",
                "link": "https://elcinema.com/work/1011214/"
            },
            {
                "name": "برنامج النهر الخالد",
                "time": "10:00 AM - 11:00 AM",
                "type": "",
                "link": ""
            }
        ]
    },
    {
        "channel_name": "إم بي سي أكشن",
        "channel_logo": "https://media0101.elcinema.com/tvguide/1130_2.png",
        "programs": [
            {
                "name": "The Promised Neverland",
                "time": "08:00 AM - 09:00 AM",
                "type": "مسلسل (2019)",
                "link": "https://elcinema.com/work/2093612/"
            },
            {
                "name": "برنامج Celebrity Car Wars",
                "time": "09:00 AM - 10:00 AM",
                "type": "",
                "link": ""
            },
            {
                "name": "برنامج وثائقيات مورشو",
                "time": "10:00 AM - 11:00 AM",
                "type": "",
                "link": ""
            }
        ]
    },
    {
        "channel_name": "إل بي سي آي",
        "channel_logo": "https://media0101.elcinema.com/tvguide/1168_2.png",
        "programs": [
            {
                "name": "فيديو كليبات",
                "time": "08:00 AM - 08:30 AM",
                "type": "",
                "link": ""
            },
            {
                "name": "نشرة الاخبار",
                "time": "08:30 AM - 09:00 AM",
                "type": "",
                "link": ""
            },
            {
                "name": "أفلام ديينية",
                "time": "09:00 AM - 12:45 PM",
                "type": "",
                "link": ""
            }
        ]
    },
    {
        "channel_name": "ميكس بالعربي",
        "channel_logo": "https://media0101.elcinema.com/tvguide/1371_2.png",
        "programs": [
            {
                "name": "برنامج في رحاب الكتاب والسنة",
                "time": "08:00 AM - 09:00 AM",
                "type": "",
                "link": ""
            },
            {
                "name": "The Yard",
                "time": "09:00 AM - 10:00 AM",
                "type": "مسلسل (2018)",
                "link": "https://elcinema.com/work/2085181/"
            },
            {
                "name": "على مر الزمان ج3",
                "time": "10:00 AM - 11:00 AM",
                "type": "مسلسل (2013)",
                "link": "https://elcinema.com/work/2025289/"
            }
        ]
    },
    {
        "channel_name": "نايل لايف",
        "channel_logo": "https://media0101.elcinema.com/tvguide/1159_2.png",
        "programs": [
            {
                "name": "برنامج صحتك بالدنيا",
                "time": "08:00 AM - 09:00 AM",
                "type": "",
                "link": ""
            },
            {
                "name": "برنامج اخبارنا الحلوة",
                "time": "09:00 AM - 10:00 AM",
                "type": "",
                "link": ""
            },
            {
                "name": "أدهم وزينات والثلاث بنات",
                "time": "10:00 AM - 10:45 AM",
                "type": "مسلسل (2003)",
                "link": "https://elcinema.com/work/1281057/"
            }
        ]
    },
    {
        "channel_name": "أو إس إن ياهلا بالعربي",
        "channel_logo": "https://media0101.elcinema.com/tvguide/1390_2.png",
        "programs": [
            {
                "name": "Six of Us S2",
                "time": "07:35 AM - 08:25 AM",
                "type": "مسلسل (2025)",
                "link": "https://elcinema.com/work/2099418/"
            },
            {
                "name": "Six of Us S2",
                "time": "08:25 AM - 09:15 AM",
                "type": "مسلسل (2025)",
                "link": "https://elcinema.com/work/2099418/"
            },
            {
                "name": "Six of Us S2",
                "time": "09:15 AM - 10:05 AM",
                "type": "مسلسل (2025)",
                "link": "https://elcinema.com/work/2099418/"
            },
            {
                "name": "Six of Us S2",
                "time": "10:05 AM - 10:55 AM",
                "type": "مسلسل (2025)",
                "link": "https://elcinema.com/work/2099418/"
            }
        ]
    },
    {
        "channel_name": "سي بي سي سفرة",
        "channel_logo": "https://media0101.elcinema.com/tvguide/1260_2.png",
        "programs": [
            {
                "name": "برنامج الشيف",
                "time": "07:00 AM - 08:30 AM",
                "type": "",
                "link": ""
            },
            {
                "name": "برنامج عيش وملح",
                "time": "08:30 AM - 09:30 AM",
                "type": "",
                "link": ""
            },
            {
                "name": "برنامج بيت التلي",
                "time": "09:30 AM - 10:30 AM",
                "type": "",
                "link": ""
            }
        ]
    },
    {
        "channel_name": "أون إي",
        "channel_logo": "https://media0101.elcinema.com/tvguide/1203_2.png",
        "programs": [
            {
                "name": "معكم منى الشاذلي",
                "time": "08:00 AM - 11:30 AM",
                "type": "ﺑﺮﻧﺎﻣﺞ (2014)",
                "link": "https://elcinema.com/work/2033089/"
            }
        ]
    },
    {
        "channel_name": "سيما",
        "channel_logo": "https://media0101.elcinema.com/tvguide/1176_2.png",
        "programs": [
            {
                "name": "لعنة المال",
                "time": "07:00 AM - 09:00 AM",
                "type": "فيلم (1987)",
                "link": "https://elcinema.com/work/1328901/"
            },
            {
                "name": "صراع المحترفين",
                "time": "09:00 AM - 11:00 AM",
                "type": "فيلم (1969)",
                "link": "https://elcinema.com/work/1009798/"
            }
        ]
    },
    {
        "channel_name": "دي إم سي",
        "channel_logo": "https://media0101.elcinema.com/tvguide/1290_2.png",
        "programs": [
            {
                "name": "صاحبة السعادة",
                "time": "07:00 AM - 09:00 AM",
                "type": "ﺑﺮﻧﺎﻣﺞ (2014)",
                "link": "https://elcinema.com/work/2029608/"
            },
            {
                "name": "لعلهم يفقهون",
                "time": "09:00 AM - 09:25 AM",
                "type": "ﺑﺮﻧﺎﻣﺞ (2017)",
                "link": "https://elcinema.com/work/2045928/"
            },
            {
                "name": "برنامج اليوم",
                "time": "09:25 AM - 09:50 AM",
                "type": "",
                "link": ""
            },
            {
                "name": "فلانتينو",
                "time": "09:50 AM - 11:00 AM",
                "type": "مسلسل (2020)",
                "link": "https://elcinema.com/work/2055489/"
            }
        ]
    },
    {
        "channel_name": "إيه تي في",
        "channel_logo": "https://media0101.elcinema.com/tvguide/1380_2.png",
        "programs": [
            {
                "name": "مسلسل",
                "time": "08:00 AM - 09:00 AM",
                "type": "",
                "link": ""
            },
            {
                "name": "مسلسل",
                "time": "09:00 AM - 10:00 AM",
                "type": "",
                "link": ""
            },
            {
                "name": "زمان الإسكافي",
                "time": "10:00 AM - 11:00 AM",
                "type": "مسلسل (1998)",
                "link": "https://elcinema.com/work/1019302/"
            }
        ]
    },
    {
        "channel_name": "روتانا دراما",
        "channel_logo": "https://media0101.elcinema.com/tvguide/1147_2.png",
        "programs": [
            {
                "name": "وتقابل حبيب",
                "time": "08:00 AM - 09:00 AM",
                "type": "مسلسل (2025)",
                "link": "https://elcinema.com/work/2089079/"
            },
            {
                "name": "من الأحد إلى الخميس",
                "time": "09:00 AM - 10:00 AM",
                "type": "مسلسل (2025)",
                "link": "https://elcinema.com/work/2088639/"
            },
            {
                "name": "زقاق الجن",
                "time": "10:00 AM - 11:00 AM",
                "type": "مسلسل (2023)",
                "link": "https://elcinema.com/work/2077858/"
            }
        ]
    },
    {
        "channel_name": "صدى البلد دراما",
        "channel_logo": "https://media0101.elcinema.com/tvguide/1227_2.png",
        "programs": [
            {
                "name": "العربجي",
                "time": "08:00 AM - 09:00 AM",
                "type": "مسلسل (2023)",
                "link": "https://elcinema.com/work/2060447/"
            },
            {
                "name": "بـ١٠٠ راجل",
                "time": "09:00 AM - 10:00 AM",
                "type": "مسلسل (2024)",
                "link": "https://elcinema.com/work/2083079/"
            },
            {
                "name": "دلع بنات",
                "time": "10:00 AM - 11:00 AM",
                "type": "مسلسل (2014)",
                "link": "https://elcinema.com/work/2029211/"
            }
        ]
    },
    {
        "channel_name": "دجلة",
        "channel_logo": "https://media0101.elcinema.com/tvguide/1385_2.png",
        "programs": [
            {
                "name": "برنامج",
                "time": "08:00 AM - 09:00 AM",
                "type": "",
                "link": ""
            },
            {
                "name": "برنامج",
                "time": "09:00 AM - 10:00 AM",
                "type": "",
                "link": ""
            },
            {
                "name": "برنامج",
                "time": "10:00 AM - 11:00 AM",
                "type": "",
                "link": ""
            }
        ]
    },
    {
        "channel_name": "تن",
        "channel_logo": "https://media0101.elcinema.com/tvguide/1280_2.png",
        "programs": [
            {
                "name": "ﺑﺮﻧﺎﻣﺞ بيت دعاء",
                "time": "08:00 AM - 09:00 AM",
                "type": "",
                "link": ""
            },
            {
                "name": "برنامج هاشتاج # فرح شعبان",
                "time": "09:00 AM - 10:00 AM",
                "type": "",
                "link": ""
            },
            {
                "name": "برنامج هلا بيك",
                "time": "10:00 AM - 11:00 AM",
                "type": "",
                "link": ""
            }
        ]
    },
    {
        "channel_name": "روتانا كلاسيك",
        "channel_logo": "https://media0101.elcinema.com/tvguide/1217_2.png",
        "programs": [
            {
                "name": "فاعل خير",
                "time": "07:00 AM - 09:00 AM",
                "type": "فيلم (1953)",
                "link": "https://elcinema.com/work/1007815/"
            },
            {
                "name": "مع الذكريات",
                "time": "09:00 AM - 11:00 AM",
                "type": "فيلم (1961)",
                "link": "https://elcinema.com/work/1004923/"
            }
        ]
    },
    {
        "channel_name": "عَمان",
        "channel_logo": "https://media0101.elcinema.com/tvguide/1298_2.png",
        "programs": [
            {
                "name": "برنامج",
                "time": "08:00 AM - 09:00 AM",
                "type": "",
                "link": ""
            },
            {
                "name": "برنامج",
                "time": "09:00 AM - 10:00 AM",
                "type": "",
                "link": ""
            },
            {
                "name": "برنامج",
                "time": "10:00 AM - 11:00 AM",
                "type": "",
                "link": ""
            }
        ]
    },
    {
        "channel_name": "أو إس إن موفيز أكشن",
        "channel_logo": "https://media0101.elcinema.com/tvguide/1211_2.png",
        "programs": [
            {
                "name": "San Andreas",
                "time": "07:20 AM - 09:15 AM",
                "type": "فيلم (2015)",
                "link": "https://elcinema.com/work/2035161/"
            },
            {
                "name": "Now You See Me",
                "time": "09:15 AM - 11:10 AM",
                "type": "فيلم (2013)",
                "link": "https://elcinema.com/work/2019704/"
            }
        ]
    },
    {
        "channel_name": "أو إس إن وان",
        "channel_logo": "https://media0101.elcinema.com/tvguide/1393_2.png",
        "programs": [
            {
                "name": "CryptoKnights",
                "time": "07:35 AM - 08:25 AM",
                "type": "ﺑﺮﻧﺎﻣﺞ (2025)",
                "link": "https://elcinema.com/work/2097121/"
            },
            {
                "name": "The Secret Life of Pets 2",
                "time": "08:25 AM - 09:50 AM",
                "type": "فيلم - ﺭﺳﻮﻡ ﻣﺘﺤﺮﻛﺔ (2019)",
                "link": "https://elcinema.com/work/2046437/"
            },
            {
                "name": "The Other Side of Fear",
                "time": "09:50 AM - 10:50 AM",
                "type": "فيلم (2020)",
                "link": "https://elcinema.com/work/2095986/"
            }
        ]
    },
    {
        "channel_name": "إم بي سي",
        "channel_logo": "https://media0101.elcinema.com/tvguide/1127_2.png",
        "programs": [
            {
                "name": "MBC في إسبوع",
                "time": "07:00 AM - 09:00 AM",
                "type": "ﺑﺮﻧﺎﻣﺞ (2016)",
                "link": "https://elcinema.com/work/2032661/"
            },
            {
                "name": "برنامج على طاولة منى",
                "time": "09:00 AM - 10:00 AM",
                "type": "",
                "link": ""
            },
            {
                "name": "برنامج اسأل ثامر",
                "time": "10:00 AM - 10:30 AM",
                "type": "",
                "link": ""
            }
        ]
    },
    {
        "channel_name": "إس بي سي",
        "channel_logo": "https://media0101.elcinema.com/tvguide/1297_2.png",
        "programs": [
            {
                "name": "الكندوش",
                "time": "08:00 AM - 09:00 AM",
                "type": "",
                "link": ""
            },
            {
                "name": "في دروب السعي مظالم",
                "time": "09:00 AM - 10:00 AM",
                "type": "مسلسل (2023)",
                "link": "https://elcinema.com/work/2077051/"
            },
            {
                "name": "برنامج مطبخ ضحي",
                "time": "10:00 AM - 11:00 AM",
                "type": "",
                "link": ""
            }
        ]
    },
    {
        "channel_name": "نسمة",
        "channel_logo": "https://media0101.elcinema.com/tvguide/1304_2.png",
        "programs": [
            {
                "name": "يوسف الصديق",
                "time": "08:00 AM - 09:00 AM",
                "type": "مسلسل (2009)",
                "link": "https://elcinema.com/work/2001287/"
            },
            {
                "name": "برنامج",
                "time": "09:00 AM - 10:00 AM",
                "type": "",
                "link": ""
            },
            {
                "name": "برنامج",
                "time": "10:00 AM - 11:00 AM",
                "type": "",
                "link": ""
            }
        ]
    },
    {
        "channel_name": "إم بي سي 3",
        "channel_logo": "https://media0101.elcinema.com/tvguide/1241_2.png",
        "programs": [
            {
                "name": "جوني جيتبوي",
                "time": "08:00 AM - 08:30 AM",
                "type": "مسلسل (2024)",
                "link": "https://elcinema.com/work/2099375/"
            },
            {
                "name": "Rugrats",
                "time": "08:30 AM - 09:00 AM",
                "type": "مسلسل - ﺭﺳﻮﻡ ﻣﺘﺤﺮﻛﺔ (1991)",
                "link": "https://elcinema.com/work/1061395/"
            },
            {
                "name": "Pac-Man and the Ghostly Adventures",
                "time": "09:00 AM - 09:30 AM",
                "type": "مسلسل - ﺭﺳﻮﻡ ﻣﺘﺤﺮﻛﺔ (2013)",
                "link": "https://elcinema.com/work/2098198/"
            },
            {
                "name": "Fantasy Patrol",
                "time": "09:30 AM - 10:00 AM",
                "type": "مسلسل - ﺭﺳﻮﻡ ﻣﺘﺤﺮﻛﺔ (2016)",
                "link": "https://elcinema.com/work/2081016/"
            },
            {
                "name": "Dogmatix And The Indomitables",
                "time": "10:00 AM - 10:30 AM",
                "type": "مسلسل - ﺭﺳﻮﻡ ﻣﺘﺤﺮﻛﺔ (2021)",
                "link": "https://elcinema.com/work/2081564/"
            }
        ]
    },
    {
        "channel_name": "الفجيرة",
        "channel_logo": "https://media0101.elcinema.com/tvguide/1302_2.png",
        "programs": [
            {
                "name": "تحت سابع أرض",
                "time": "08:00 AM - 09:00 AM",
                "type": "مسلسل (2025)",
                "link": "https://elcinema.com/work/2089297/"
            },
            {
                "name": "برنامج",
                "time": "09:00 AM - 10:00 AM",
                "type": "",
                "link": ""
            },
            {
                "name": "حب بين السطور",
                "time": "10:00 AM - 11:00 AM",
                "type": "مسلسل (2023)",
                "link": "https://elcinema.com/work/2079433/"
            }
        ]
    },
    {
        "channel_name": "دي إم سي دراما",
        "channel_logo": "https://media0101.elcinema.com/tvguide/1292_2.png",
        "programs": [
            {
                "name": "لمس أكتاف",
                "time": "08:00 AM - 09:00 AM",
                "type": "مسلسل (2019)",
                "link": "https://elcinema.com/work/2054313/"
            },
            {
                "name": "زينهم",
                "time": "09:00 AM - 10:00 AM",
                "type": "مسلسل (2023)",
                "link": "https://elcinema.com/work/2082777/"
            },
            {
                "name": "زينهم",
                "time": "10:00 AM - 11:00 AM",
                "type": "مسلسل (2023)",
                "link": "https://elcinema.com/work/2082777/"
            }
        ]
    },
    {
        "channel_name": "السعودية",
        "channel_logo": "https://media0101.elcinema.com/tvguide/1352_2.png",
        "programs": [
            {
                "name": "برنامج دورينا غير",
                "time": "06:30 AM - 08:30 AM",
                "type": "",
                "link": ""
            },
            {
                "name": "برنامج",
                "time": "08:30 AM - 09:00 AM",
                "type": "",
                "link": ""
            },
            {
                "name": "برنامج",
                "time": "09:00 AM - 10:00 AM",
                "type": "",
                "link": ""
            },
            {
                "name": "برنامج",
                "time": "10:00 AM - 11:00 AM",
                "type": "",
                "link": ""
            }
        ]
    },
    {
        "channel_name": "قناة مصر الأولى",
        "channel_logo": "https://media0101.elcinema.com/tvguide/1101_2.png",
        "programs": [
            {
                "name": "لهفة",
                "time": "08:00 AM - 08:40 AM",
                "type": "مسلسل (2015)",
                "link": "https://elcinema.com/work/2017262/"
            },
            {
                "name": "المغامرون الخمسة",
                "time": "08:40 AM - 09:00 AM",
                "type": "مسلسل (2002)",
                "link": "https://elcinema.com/work/2039218/"
            },
            {
                "name": "نشرة الثالثة",
                "time": "09:00 AM - 10:00 AM",
                "type": "",
                "link": ""
            },
            {
                "name": "برنامج",
                "time": "10:00 AM - 11:00 AM",
                "type": "",
                "link": ""
            }
        ]
    },
    {
        "channel_name": "بي إن سيريس",
        "channel_logo": "https://media0101.elcinema.com/tvguide/1327_2.png",
        "programs": [
            {
                "name": "The Lady",
                "time": "08:00 AM - 09:00 AM",
                "type": "مسلسل (2026)",
                "link": "https://elcinema.com/work/2099287/"
            },
            {
                "name": "Station Eleven",
                "time": "09:00 AM - 10:00 AM",
                "type": "مسلسل (2021)",
                "link": "https://elcinema.com/work/2088207/"
            },
            {
                "name": "The Challenge: All Stars S5",
                "time": "10:00 AM - 11:00 AM",
                "type": "مسلسل (2025)",
                "link": "https://elcinema.com/work/2097660/"
            }
        ]
    },
    {
        "channel_name": "النهار دراما",
        "channel_logo": "https://media0101.elcinema.com/tvguide/1223_2.png",
        "programs": [
            {
                "name": "لن أعيش في جلباب أبي",
                "time": "08:00 AM - 09:00 AM",
                "type": "مسلسل (1996)",
                "link": "https://elcinema.com/work/1010312/"
            },
            {
                "name": "قطر صغنطوط",
                "time": "09:00 AM - 10:00 AM",
                "type": "مسلسل (2026)",
                "link": "https://elcinema.com/work/2097314/"
            },
            {
                "name": "الريان",
                "time": "10:00 AM - 11:00 AM",
                "type": "مسلسل (2011)",
                "link": "https://elcinema.com/work/1603341/"
            }
        ]
    },
    {
        "channel_name": "إم تي في",
        "channel_logo": "https://media0101.elcinema.com/tvguide/1296_2.png",
        "programs": [
            {
                "name": "أخبار",
                "time": "08:00 AM - 09:00 AM",
                "type": "",
                "link": ""
            },
            {
                "name": "برنامج بيروت اليوم",
                "time": "09:00 AM - 10:30 AM",
                "type": "",
                "link": ""
            }
        ]
    },
    {
        "channel_name": "إم بي سي 5",
        "channel_logo": "https://media0101.elcinema.com/tvguide/1354_2.png",
        "programs": [
            {
                "name": "برنامج براد و صينية",
                "time": "07:30 AM - 08:30 AM",
                "type": "",
                "link": ""
            },
            {
                "name": "ولاد العم",
                "time": "08:30 AM - 09:30 AM",
                "type": "مسلسل (2021)",
                "link": "https://elcinema.com/work/2068527/"
            },
            {
                "name": "يوم ملقاك",
                "time": "09:30 AM - 10:20 AM",
                "type": "مسلسل (2025)",
                "link": "https://elcinema.com/work/2091851/"
            },
            {
                "name": "وتبقى ليلة",
                "time": "10:20 AM - 11:09 AM",
                "type": "",
                "link": ""
            }
        ]
    },
    {
        "channel_name": "أو إس إن كوميدي",
        "channel_logo": "https://media0101.elcinema.com/tvguide/1257_2.png",
        "programs": [
            {
                "name": "The Big Bang Theory S12",
                "time": "08:00 AM - 08:25 AM",
                "type": "مسلسل (2018)",
                "link": "https://elcinema.com/work/2062103/"
            },
            {
                "name": "The Big Bang Theory S12",
                "time": "08:25 AM - 08:50 AM",
                "type": "مسلسل (2018)",
                "link": "https://elcinema.com/work/2062103/"
            },
            {
                "name": "The Big Bang Theory S12",
                "time": "08:50 AM - 09:15 AM",
                "type": "مسلسل (2018)",
                "link": "https://elcinema.com/work/2062103/"
            },
            {
                "name": "The Big Bang Theory S12",
                "time": "09:15 AM - 09:40 AM",
                "type": "مسلسل (2018)",
                "link": "https://elcinema.com/work/2062103/"
            },
            {
                "name": "The Big Bang Theory S12",
                "time": "09:40 AM - 10:05 AM",
                "type": "مسلسل (2018)",
                "link": "https://elcinema.com/work/2062103/"
            },
            {
                "name": "The Big Bang Theory S12",
                "time": "10:05 AM - 10:30 AM",
                "type": "مسلسل (2018)",
                "link": "https://elcinema.com/work/2062103/"
            }
        ]
    },
    {
        "channel_name": "دبي زمان",
        "channel_logo": "https://media0101.elcinema.com/tvguide/1283_2.png",
        "programs": [
            {
                "name": "برنامج أسماء وأمثال",
                "time": "08:00 AM - 09:17 AM",
                "type": "",
                "link": ""
            },
            {
                "name": "برنامج نجم وسما",
                "time": "09:17 AM - 10:05 AM",
                "type": "",
                "link": ""
            },
            {
                "name": "برنامج عذب المعاني",
                "time": "10:05 AM - 11:15 AM",
                "type": "",
                "link": ""
            }
        ]
    },
    {
        "channel_name": "الشارقة",
        "channel_logo": "https://media0101.elcinema.com/tvguide/1188_2.png",
        "programs": [
            {
                "name": "برنامج",
                "time": "08:00 AM - 09:00 AM",
                "type": "",
                "link": ""
            },
            {
                "name": "برنامج",
                "time": "09:00 AM - 09:30 AM",
                "type": "",
                "link": ""
            },
            {
                "name": "برنامج نصيحة طبيب",
                "time": "09:30 AM - 09:45 AM",
                "type": "",
                "link": ""
            },
            {
                "name": "النويلاتي",
                "time": "09:45 AM - 10:30 AM",
                "type": "مسلسل (2026)",
                "link": "https://elcinema.com/work/2097140/"
            }
        ]
    },
    {
        "channel_name": "الرشيد",
        "channel_logo": "https://media0101.elcinema.com/tvguide/1306_2.png",
        "programs": [
            {
                "name": "اخبار",
                "time": "08:00 AM - 09:00 AM",
                "type": "",
                "link": ""
            },
            {
                "name": "أخبار",
                "time": "09:00 AM - 10:00 AM",
                "type": "",
                "link": ""
            },
            {
                "name": "مغامرات سندباد",
                "time": "10:00 AM - 10:20 AM",
                "type": "مسلسل - ﺭﺳﻮﻡ ﻣﺘﺤﺮﻛﺔ (1975)",
                "link": "https://elcinema.com/work/1010934/"
            },
            {
                "name": "The Tom and Jerry Show",
                "time": "10:20 AM - 11:00 AM",
                "type": "مسلسل - ﺭﺳﻮﻡ ﻣﺘﺤﺮﻛﺔ (2014)",
                "link": "https://elcinema.com/work/2052624/"
            }
        ]
    },
    {
        "channel_name": "إم بي سي دراما +",
        "channel_logo": "https://media0101.elcinema.com/tvguide/1131_2.png",
        "programs": [
            {
                "name": "بيبي",
                "time": "06:55 AM - 10:15 AM",
                "type": "مسلسل (2022)",
                "link": "https://elcinema.com/work/2070924/"
            },
            {
                "name": "ضرغام",
                "time": "10:15 AM - 02:00 PM",
                "type": "مسلسل (2025)",
                "link": "https://elcinema.com/work/2096593/"
            }
        ]
    },
    {
        "channel_name": "ناشيونال جيوجرافيك",
        "channel_logo": "https://media0101.elcinema.com/tvguide/1275_2.png",
        "programs": [
            {
                "name": "برنامج تحقيقات الكوارث الجوية",
                "time": "07:55 AM - 08:40 AM",
                "type": "",
                "link": ""
            },
            {
                "name": "برنامج كوكبنا العجيب",
                "time": "08:40 AM - 09:30 AM",
                "type": "",
                "link": ""
            },
            {
                "name": "برنامج الأشعة السينية للأرض",
                "time": "09:30 AM - 10:15 AM",
                "type": "",
                "link": ""
            },
            {
                "name": "Titanic: A'ad Khamsa Wa E'shreen A'aaman Ma'a James Cameron",
                "time": "10:15 AM - 11:00 AM",
                "type": "",
                "link": ""
            }
        ]
    },
    {
        "channel_name": "السعيدة",
        "channel_logo": "https://media0101.elcinema.com/tvguide/1339_2.png",
        "programs": [
            {
                "name": "برنامج",
                "time": "07:00 AM - 08:30 AM",
                "type": "",
                "link": ""
            },
            {
                "name": "فقرة غنائية",
                "time": "08:30 AM - 10:20 AM",
                "type": "",
                "link": ""
            },
            {
                "name": "همي همك ج7: قرية مركوضة",
                "time": "10:20 AM - 11:15 AM",
                "type": "مسلسل (2015)",
                "link": "https://elcinema.com/work/2058384/"
            }
        ]
    }
]